{
"meta":{"test_sets":[],"test_metrics":[],"learn_metrics":[{"best_value":"Min","name":"RMSE"}],"launch_mode":"Train","parameters":"","iteration_count":1000,"learn_sets":["learn"],"name":"experiment"},
"iterations":[
{"learn":[14.65519095],"iteration":0,"passed_time":0.1351924334,"remaining_time":135.057241},
{"learn":[14.21081993],"iteration":1,"passed_time":0.1369388262,"remaining_time":68.33247429},
{"learn":[13.8035531],"iteration":2,"passed_time":0.1388939245,"remaining_time":46.1590809},
{"learn":[13.39571072],"iteration":3,"passed_time":0.1406493475,"remaining_time":35.02168753},
{"learn":[12.98263459],"iteration":4,"passed_time":0.1425529648,"remaining_time":28.36803999},
{"learn":[12.63913151],"iteration":5,"passed_time":0.1449139993,"remaining_time":24.00741922},
{"learn":[12.27920425],"iteration":6,"passed_time":0.1467821042,"remaining_time":20.82208992},
{"learn":[11.95868616],"iteration":7,"passed_time":0.1484391278,"remaining_time":18.40645185},
{"learn":[11.62185467],"iteration":8,"passed_time":0.150665297,"remaining_time":16.58992326},
{"learn":[11.28145648],"iteration":9,"passed_time":0.1523669293,"remaining_time":15.084326},
{"learn":[10.95740504],"iteration":10,"passed_time":0.1542853625,"remaining_time":13.87165668},
{"learn":[10.68538595],"iteration":11,"passed_time":0.1559832393,"remaining_time":12.84262004},
{"learn":[10.43355466],"iteration":12,"passed_time":0.157579934,"remaining_time":11.96395345},
{"learn":[10.14507473],"iteration":13,"passed_time":0.1593599177,"remaining_time":11.22349134},
{"learn":[9.857301163],"iteration":14,"passed_time":0.1608881744,"remaining_time":10.56499012},
{"learn":[9.585425256],"iteration":15,"passed_time":0.1625562348,"remaining_time":9.99720844},
{"learn":[9.330765093],"iteration":16,"passed_time":0.1641573555,"remaining_time":9.492157674},
{"learn":[9.097033661],"iteration":17,"passed_time":0.1659439907,"remaining_time":9.053166605},
{"learn":[8.857063646],"iteration":18,"passed_time":0.1678566818,"remaining_time":8.666705521},
{"learn":[8.638367328],"iteration":19,"passed_time":0.1698793109,"remaining_time":8.324086235},
{"learn":[8.425649621],"iteration":20,"passed_time":0.1715662876,"remaining_time":7.99825693},
{"learn":[8.226514049],"iteration":21,"passed_time":0.1735279441,"remaining_time":7.714105878},
{"learn":[8.021378706],"iteration":22,"passed_time":0.1753257626,"remaining_time":7.447533482},
{"learn":[7.835412841],"iteration":23,"passed_time":0.1771816356,"remaining_time":7.205386516},
{"learn":[7.646091635],"iteration":24,"passed_time":0.1788282614,"remaining_time":6.974302194},
{"learn":[7.465332262],"iteration":25,"passed_time":0.1807270221,"remaining_time":6.77031229},
{"learn":[7.290925915],"iteration":26,"passed_time":0.1825527703,"remaining_time":6.578660945},
{"learn":[7.135381278],"iteration":27,"passed_time":0.1841744133,"remaining_time":6.393483205},
{"learn":[6.974058355],"iteration":28,"passed_time":0.1859249213,"remaining_time":6.225279263},
{"learn":[6.809491711],"iteration":29,"passed_time":0.1875552809,"remaining_time":6.064287417},
{"learn":[6.674512035],"iteration":30,"passed_time":0.1892807189,"remaining_time":5.916548924},
{"learn":[6.52857194],"iteration":31,"passed_time":0.1911286467,"remaining_time":5.781641564},
{"learn":[6.403575305],"iteration":32,"passed_time":0.1927704616,"remaining_time":5.648758677},
{"learn":[6.264860626],"iteration":33,"passed_time":0.1945633795,"remaining_time":5.52788896},
{"learn":[6.132627266],"iteration":34,"passed_time":0.1962157778,"remaining_time":5.409949301},
{"learn":[6.006568879],"iteration":35,"passed_time":0.1976861458,"remaining_time":5.293595683},
{"learn":[5.890954868],"iteration":36,"passed_time":0.1993302011,"remaining_time":5.187972532},
{"learn":[5.787556543],"iteration":37,"passed_time":0.2009914189,"remaining_time":5.088256446},
{"learn":[5.681632486],"iteration":38,"passed_time":0.2027090755,"remaining_time":4.994959526},
{"learn":[5.579901344],"iteration":39,"passed_time":0.2044766402,"remaining_time":4.907439365},
{"learn":[5.48534043],"iteration":40,"passed_time":0.206229927,"remaining_time":4.823768292},
{"learn":[5.396943817],"iteration":41,"passed_time":0.208010356,"remaining_time":4.744617167},
{"learn":[5.318203303],"iteration":42,"passed_time":0.2093869805,"remaining_time":4.660077683},
{"learn":[5.231263761],"iteration":43,"passed_time":0.2108183398,"remaining_time":4.580507565},
{"learn":[5.151637936],"iteration":44,"passed_time":0.2124080681,"remaining_time":4.507771223},
{"learn":[5.0729768],"iteration":45,"passed_time":0.2138845023,"remaining_time":4.43577859},
{"learn":[4.996464284],"iteration":46,"passed_time":0.2155494487,"remaining_time":4.370609034},
{"learn":[4.923850512],"iteration":47,"passed_time":0.2169250808,"remaining_time":4.302347436},
{"learn":[4.857365157],"iteration":48,"passed_time":0.2188178556,"remaining_time":4.246852667},
{"learn":[4.790774575],"iteration":49,"passed_time":0.220092447,"remaining_time":4.181756493},
{"learn":[4.730862146],"iteration":50,"passed_time":0.221250225,"remaining_time":4.116989481},
{"learn":[4.66895278],"iteration":51,"passed_time":0.2228303464,"remaining_time":4.062368623},
{"learn":[4.613377732],"iteration":52,"passed_time":0.2246574139,"remaining_time":4.014161715},
{"learn":[4.560256224],"iteration":53,"passed_time":0.2261592016,"remaining_time":3.961974161},
{"learn":[4.50683163],"iteration":54,"passed_time":0.2273206979,"remaining_time":3.9057829},
{"learn":[4.457509166],"iteration":55,"passed_time":0.2285151365,"remaining_time":3.852112301},
{"learn":[4.409546496],"iteration":56,"passed_time":0.2300423455,"remaining_time":3.805788278},
{"learn":[4.360737248],"iteration":57,"passed_time":0.2314581708,"remaining_time":3.759199946},
{"learn":[4.316978363],"iteration":58,"passed_time":0.2327328863,"remaining_time":3.711892306},
{"learn":[4.276685971],"iteration":59,"passed_time":0.2343042883,"remaining_time":3.670767184},
{"learn":[4.236727107],"iteration":60,"passed_time":0.2357716078,"remaining_time":3.629336716},
{"learn":[4.193819622],"iteration":61,"passed_time":0.2370163323,"remaining_time":3.585827737},
{"learn":[4.151077331],"iteration":62,"passed_time":0.2382209017,"remaining_time":3.543063252},
{"learn":[4.114691162],"iteration":63,"passed_time":0.2396297449,"remaining_time":3.50458502},
{"learn":[4.078831316],"iteration":64,"passed_time":0.2410075394,"remaining_time":3.466800759},
{"learn":[4.044177194],"iteration":65,"passed_time":0.2425783675,"remaining_time":3.432851443},
{"learn":[4.008930341],"iteration":66,"passed_time":0.2440391258,"remaining_time":3.398335887},
{"learn":[3.973862349],"iteration":67,"passed_time":0.2449928691,"remaining_time":3.357843441},
{"learn":[3.946993186],"iteration":68,"passed_time":0.2457971854,"remaining_time":3.316480864},
{"learn":[3.917067163],"iteration":69,"passed_time":0.2472824803,"remaining_time":3.285324381},
{"learn":[3.891444213],"iteration":70,"passed_time":0.2482970688,"remaining_time":3.248844745},
{"learn":[3.862805577],"iteration":71,"passed_time":0.2495275013,"remaining_time":3.216132238},
{"learn":[3.839930384],"iteration":72,"passed_time":0.2510757961,"remaining_time":3.188318671},
{"learn":[3.817601936],"iteration":73,"passed_time":0.2522214608,"remaining_time":3.156176658},
{"learn":[3.794485243],"iteration":74,"passed_time":0.2537291191,"remaining_time":3.129325803},
{"learn":[3.766689896],"iteration":75,"passed_time":0.2547961618,"remaining_time":3.097784914},
{"learn":[3.746730573],"iteration":76,"passed_time":0.2563099871,"remaining_time":3.072391144},
{"learn":[3.72677993],"iteration":77,"passed_time":0.2579208337,"remaining_time":3.048756521},
{"learn":[3.707072395],"iteration":78,"passed_time":0.2594837181,"remaining_time":3.025120309},
{"learn":[3.687103647],"iteration":79,"passed_time":0.2608685238,"remaining_time":2.999988024},
{"learn":[3.673746219],"iteration":80,"passed_time":0.2622156544,"remaining_time":2.975014647},
{"learn":[3.655799074],"iteration":81,"passed_time":0.2634386811,"remaining_time":2.949228162},
{"learn":[3.6399279],"iteration":82,"passed_time":0.2645114678,"remaining_time":2.922373687},
{"learn":[3.622138959],"iteration":83,"passed_time":0.2657378888,"remaining_time":2.897808407},
{"learn":[3.607397845],"iteration":84,"passed_time":0.2669073111,"remaining_time":2.873178702},
{"learn":[3.59313726],"iteration":85,"passed_time":0.268226971,"remaining_time":2.850691296},
{"learn":[3.57851678],"iteration":86,"passed_time":0.2693348124,"remaining_time":2.826467629},
{"learn":[3.565204518],"iteration":87,"passed_time":0.2704467032,"remaining_time":2.802811288},
{"learn":[3.553688411],"iteration":88,"passed_time":0.2711532113,"remaining_time":2.775512084},
{"learn":[3.539530804],"iteration":89,"passed_time":0.2725150232,"remaining_time":2.755429679},
{"learn":[3.527146074],"iteration":90,"passed_time":0.2740335981,"remaining_time":2.737324623},
{"learn":[3.515554106],"iteration":91,"passed_time":0.2751994827,"remaining_time":2.716099242},
{"learn":[3.503489925],"iteration":92,"passed_time":0.2765631317,"remaining_time":2.697233983},
{"learn":[3.493410522],"iteration":93,"passed_time":0.277918163,"remaining_time":2.678658039},
{"learn":[3.482553826],"iteration":94,"passed_time":0.2792168492,"remaining_time":2.659907879},
{"learn":[3.4714116],"iteration":95,"passed_time":0.2802902431,"remaining_time":2.639399789},
{"learn":[3.461823319],"iteration":96,"passed_time":0.2814810167,"remaining_time":2.620385135},
{"learn":[3.459494441],"iteration":97,"passed_time":0.2819855407,"remaining_time":2.595417935},
{"learn":[3.449168139],"iteration":98,"passed_time":0.2834150332,"remaining_time":2.57936308},
{"learn":[3.437970075],"iteration":99,"passed_time":0.2844977296,"remaining_time":2.560479566},
{"learn":[3.427231179],"iteration":100,"passed_time":0.2862769959,"remaining_time":2.548148706},
{"learn":[3.418868521],"iteration":101,"passed_time":0.2872371453,"remaining_time":2.528813299},
{"learn":[3.410148661],"iteration":102,"passed_time":0.2884432358,"remaining_time":2.511976529},
{"learn":[3.402148444],"iteration":103,"passed_time":0.2898459253,"remaining_time":2.497134126},
{"learn":[3.393036955],"iteration":104,"passed_time":0.2907276421,"remaining_time":2.478107044},
{"learn":[3.38321018],"iteration":105,"passed_time":0.2922302052,"remaining_time":2.464658523},
{"learn":[3.375613366],"iteration":106,"passed_time":0.2934301159,"remaining_time":2.448907416},
{"learn":[3.367861459],"iteration":107,"passed_time":0.2947514035,"remaining_time":2.434428258},
{"learn":[3.36066539],"iteration":108,"passed_time":0.2958937976,"remaining_time":2.418728199},
{"learn":[3.352260255],"iteration":109,"passed_time":0.2969873814,"remaining_time":2.402897904},
{"learn":[3.346410547],"iteration":110,"passed_time":0.2987073333,"remaining_time":2.392349723},
{"learn":[3.3394146],"iteration":111,"passed_time":0.2996098038,"remaining_time":2.37547773},
{"learn":[3.333405698],"iteration":112,"passed_time":0.3005140118,"remaining_time":2.358902022},
{"learn":[3.326352329],"iteration":113,"passed_time":0.3013737312,"remaining_time":2.34225549},
{"learn":[3.320837618],"iteration":114,"passed_time":0.3022369338,"remaining_time":2.325910317},
{"learn":[3.316520239],"iteration":115,"passed_time":0.3031368375,"remaining_time":2.310111762},
{"learn":[3.310998981],"iteration":116,"passed_time":0.3044597051,"remaining_time":2.297759996},
{"learn":[3.303328192],"iteration":117,"passed_time":0.3056443882,"remaining_time":2.284562292},
{"learn":[3.297729615],"iteration":118,"passed_time":0.3066107326,"remaining_time":2.269950045},
{"learn":[3.29151963],"iteration":119,"passed_time":0.3077939086,"remaining_time":2.25715533},
{"learn":[3.285505736],"iteration":120,"passed_time":0.3092248674,"remaining_time":2.246352549},
{"learn":[3.28106799],"iteration":121,"passed_time":0.3106164797,"remaining_time":2.235420239},
{"learn":[3.276331551],"iteration":122,"passed_time":0.3117939701,"remaining_time":2.223116356},
{"learn":[3.271798137],"iteration":123,"passed_time":0.3133325327,"remaining_time":2.213542731},
{"learn":[3.268077771],"iteration":124,"passed_time":0.3144773283,"remaining_time":2.201341298},
{"learn":[3.262818483],"iteration":125,"passed_time":0.3154775137,"remaining_time":2.188312278},
{"learn":[3.257951106],"iteration":126,"passed_time":0.3167041066,"remaining_time":2.177029016},
{"learn":[3.253042667],"iteration":127,"passed_time":0.3178058723,"remaining_time":2.165052505},
{"learn":[3.247772978],"iteration":128,"passed_time":0.3188532261,"remaining_time":2.152877209},
{"learn":[3.243677775],"iteration":129,"passed_time":0.3198544132,"remaining_time":2.14056415},
{"learn":[3.239477993],"iteration":130,"passed_time":0.3208275149,"remaining_time":2.128237485},
{"learn":[3.234588714],"iteration":131,"passed_time":0.3217159642,"remaining_time":2.115526189},
{"learn":[3.229469679],"iteration":132,"passed_time":0.322889744,"remaining_time":2.104852692},
{"learn":[3.223687009],"iteration":133,"passed_time":0.3242378065,"remaining_time":2.095447317},
{"learn":[3.218099222],"iteration":134,"passed_time":0.3253285831,"remaining_time":2.084512773},
{"learn":[3.213820392],"iteration":135,"passed_time":0.3262221128,"remaining_time":2.072469893},
{"learn":[3.209981979],"iteration":136,"passed_time":0.3280711784,"remaining_time":2.066608956},
{"learn":[3.206413908],"iteration":137,"passed_time":0.3296558488,"remaining_time":2.05915465},
{"learn":[3.201631929],"iteration":138,"passed_time":0.3311369228,"remaining_time":2.051143097},
{"learn":[3.197149927],"iteration":139,"passed_time":0.3328252007,"remaining_time":2.044497661},
{"learn":[3.191397521],"iteration":140,"passed_time":0.3346882343,"remaining_time":2.038987186},
{"learn":[3.187655867],"iteration":141,"passed_time":0.33613419,"remaining_time":2.031007993},
{"learn":[3.183043254],"iteration":142,"passed_time":0.3377176027,"remaining_time":2.023943955},
{"learn":[3.178647055],"iteration":143,"passed_time":0.338616319,"remaining_time":2.012885896},
{"learn":[3.174397451],"iteration":144,"passed_time":0.3401521196,"remaining_time":2.005724568},
{"learn":[3.171108919],"iteration":145,"passed_time":0.3415904108,"remaining_time":1.998069937},
{"learn":[3.166803349],"iteration":146,"passed_time":0.3433150018,"remaining_time":1.992161201},
{"learn":[3.161991808],"iteration":147,"passed_time":0.3449315604,"remaining_time":1.985687091},
{"learn":[3.161325613],"iteration":148,"passed_time":0.3455150315,"remaining_time":1.973377798},
{"learn":[3.157120307],"iteration":149,"passed_time":0.3468710036,"remaining_time":1.965602354},
{"learn":[3.153258877],"iteration":150,"passed_time":0.3484305206,"remaining_time":1.959056371},
{"learn":[3.150778841],"iteration":151,"passed_time":0.3497629991,"remaining_time":1.951309363},
{"learn":[3.145688114],"iteration":152,"passed_time":0.3512634303,"remaining_time":1.944575984},
{"learn":[3.141982869],"iteration":153,"passed_time":0.3524502774,"remaining_time":1.936187887},
{"learn":[3.140090631],"iteration":154,"passed_time":0.3538078531,"remaining_time":1.928823457},
{"learn":[3.136402999],"iteration":155,"passed_time":0.3546943744,"remaining_time":1.918987513},
{"learn":[3.13258511],"iteration":156,"passed_time":0.3563768517,"remaining_time":1.913539401},
{"learn":[3.12997708],"iteration":157,"passed_time":0.3577169554,"remaining_time":1.906314408},
{"learn":[3.125377507],"iteration":158,"passed_time":0.3593732874,"remaining_time":1.900836067},
{"learn":[3.12209243],"iteration":159,"passed_time":0.3610286466,"remaining_time":1.895400394},
{"learn":[3.119213853],"iteration":160,"passed_time":0.3626219682,"remaining_time":1.889688393},
{"learn":[3.116494977],"iteration":161,"passed_time":0.3641338158,"remaining_time":1.883605788},
{"learn":[3.114285527],"iteration":162,"passed_time":0.3653983914,"remaining_time":1.876309531},
{"learn":[3.110506935],"iteration":163,"passed_time":0.3673462822,"remaining_time":1.872570072},
{"learn":[3.106034589],"iteration":164,"passed_time":0.3689049164,"remaining_time":1.866882456},
{"learn":[3.103997486],"iteration":165,"passed_time":0.3706665741,"remaining_time":1.862264595},
{"learn":[3.10015867],"iteration":166,"passed_time":0.3723151708,"remaining_time":1.857116989},
{"learn":[3.096404007],"iteration":167,"passed_time":0.3737999895,"remaining_time":1.851199948},
{"learn":[3.094843448],"iteration":168,"passed_time":0.375229943,"remaining_time":1.845065578},
{"learn":[3.092371627],"iteration":169,"passed_time":0.376699142,"remaining_time":1.839178164},
{"learn":[3.088848452],"iteration":170,"passed_time":0.3785000869,"remaining_time":1.834950713},
{"learn":[3.08497182],"iteration":171,"passed_time":0.3802502833,"remaining_time":1.830507178},
{"learn":[3.080411203],"iteration":172,"passed_time":0.3819076202,"remaining_time":1.825650878},
{"learn":[3.076855065],"iteration":173,"passed_time":0.3832795888,"remaining_time":1.819476669},
{"learn":[3.073520641],"iteration":174,"passed_time":0.385127934,"remaining_time":1.815603117},
{"learn":[3.072034586],"iteration":175,"passed_time":0.3864050301,"remaining_time":1.809078096},
{"learn":[3.068180761],"iteration":176,"passed_time":0.3879556114,"remaining_time":1.803884001},
{"learn":[3.066444694],"iteration":177,"passed_time":0.3893038987,"remaining_time":1.797796656},
{"learn":[3.063582438],"iteration":178,"passed_time":0.3910749871,"remaining_time":1.793701477},
{"learn":[3.059439421],"iteration":179,"passed_time":0.3926582416,"remaining_time":1.788776434},
{"learn":[3.056716842],"iteration":180,"passed_time":0.3942693201,"remaining_time":1.784014216},
{"learn":[3.053622028],"iteration":181,"passed_time":0.3955068031,"remaining_time":1.777607499},
{"learn":[3.051097872],"iteration":182,"passed_time":0.3971207063,"remaining_time":1.772937798},
{"learn":[3.047099448],"iteration":183,"passed_time":0.398692687,"remaining_time":1.768115395},
{"learn":[3.045232955],"iteration":184,"passed_time":0.3999756998,"remaining_time":1.76205511},
{"learn":[3.042375605],"iteration":185,"passed_time":0.4012284056,"remaining_time":1.75591356},
{"learn":[3.040154978],"iteration":186,"passed_time":0.402183022,"remaining_time":1.748528326},
{"learn":[3.036738506],"iteration":187,"passed_time":0.4031194839,"remaining_time":1.74113309},
{"learn":[3.034796301],"iteration":188,"passed_time":0.404006227,"remaining_time":1.733592858},
{"learn":[3.033362131],"iteration":189,"passed_time":0.4050728111,"remaining_time":1.726889352},
{"learn":[3.030138627],"iteration":190,"passed_time":0.4060907638,"remaining_time":1.72003889},
{"learn":[3.027700794],"iteration":191,"passed_time":0.4071445093,"remaining_time":1.71339981},
{"learn":[3.024929194],"iteration":192,"passed_time":0.4081519507,"remaining_time":1.706624996},
{"learn":[3.021232392],"iteration":193,"passed_time":0.4091366158,"remaining_time":1.699815012},
{"learn":[3.019965653],"iteration":194,"passed_time":0.4100723075,"remaining_time":1.692862603},
{"learn":[3.018820112],"iteration":195,"passed_time":0.4109569592,"remaining_time":1.68576222},
{"learn":[3.016091834],"iteration":196,"passed_time":0.4119637722,"remaining_time":1.679222889},
{"learn":[3.014886505],"iteration":197,"passed_time":0.4128913717,"remaining_time":1.672418586},
{"learn":[3.012559105],"iteration":198,"passed_time":0.4137079086,"remaining_time":1.665226306},
{"learn":[3.010475245],"iteration":199,"passed_time":0.4146606254,"remaining_time":1.658642502},
{"learn":[3.007509043],"iteration":200,"passed_time":0.415629817,"remaining_time":1.652180218},
{"learn":[3.004920814],"iteration":201,"passed_time":0.416512958,"remaining_time":1.645432378},
{"learn":[3.004201238],"iteration":202,"passed_time":0.4171655416,"remaining_time":1.637837126},
{"learn":[3.002206801],"iteration":203,"passed_time":0.4179766032,"remaining_time":1.630928314},
{"learn":[3.000496679],"iteration":204,"passed_time":0.4187643193,"remaining_time":1.623988458},
{"learn":[2.9985606],"iteration":205,"passed_time":0.419573247,"remaining_time":1.617190088},
{"learn":[2.997202759],"iteration":206,"passed_time":0.4203626217,"remaining_time":1.610374681},
{"learn":[2.993011246],"iteration":207,"passed_time":0.4212582532,"remaining_time":1.60402181},
{"learn":[2.992108683],"iteration":208,"passed_time":0.4221196307,"remaining_time":1.597591521},
{"learn":[2.989906417],"iteration":209,"passed_time":0.4229336837,"remaining_time":1.591036239},
{"learn":[2.987085208],"iteration":210,"passed_time":0.4237777694,"remaining_time":1.584647678},
{"learn":[2.983729064],"iteration":211,"passed_time":0.4245510116,"remaining_time":1.5780481},
{"learn":[2.982548843],"iteration":212,"passed_time":0.4253401724,"remaining_time":1.571562045},
{"learn":[2.980575108],"iteration":213,"passed_time":0.4262516695,"remaining_time":1.565578562},
{"learn":[2.979479346],"iteration":214,"passed_time":0.4272010806,"remaining_time":1.559780689},
{"learn":[2.978064317],"iteration":215,"passed_time":0.4280499411,"remaining_time":1.553662749},
{"learn":[2.976974833],"iteration":216,"passed_time":0.4288467911,"remaining_time":1.547405703},
{"learn":[2.976394392],"iteration":217,"passed_time":0.4294070382,"remaining_time":1.540350018},
{"learn":[2.97330319],"iteration":218,"passed_time":0.4302421494,"remaining_time":1.534333875},
{"learn":[2.971550013],"iteration":219,"passed_time":0.4310159467,"remaining_time":1.528147447},
{"learn":[2.969104204],"iteration":220,"passed_time":0.4317865365,"remaining_time":1.521998696},
{"learn":[2.968155464],"iteration":221,"passed_time":0.4325529445,"remaining_time":1.515883742},
{"learn":[2.965509492],"iteration":222,"passed_time":0.4334042064,"remaining_time":1.510112414},
{"learn":[2.963383698],"iteration":223,"passed_time":0.4341618514,"remaining_time":1.5040607},
{"learn":[2.962344254],"iteration":224,"passed_time":0.4349442657,"remaining_time":1.49814136},
{"learn":[2.961587319],"iteration":225,"passed_time":0.4358017218,"remaining_time":1.492524481},
{"learn":[2.959610419],"iteration":226,"passed_time":0.436610028,"remaining_time":1.486782166},
{"learn":[2.956935419],"iteration":227,"passed_time":0.4373942305,"remaining_time":1.481001517},
{"learn":[2.955610733],"iteration":228,"passed_time":0.4382134908,"remaining_time":1.475382539},
{"learn":[2.952052136],"iteration":229,"passed_time":0.4390396198,"remaining_time":1.469828292},
{"learn":[2.951036521],"iteration":230,"passed_time":0.4400804847,"remaining_time":1.465029839},
{"learn":[2.949900048],"iteration":231,"passed_time":0.4410148194,"remaining_time":1.459911126},
{"learn":[2.947847372],"iteration":232,"passed_time":0.4418309082,"remaining_time":1.454439084},
{"learn":[2.946221526],"iteration":233,"passed_time":0.4426283466,"remaining_time":1.448945784},
{"learn":[2.944852639],"iteration":234,"passed_time":0.443438284,"remaining_time":1.443533137},
{"learn":[2.943488008],"iteration":235,"passed_time":0.4443667153,"remaining_time":1.438543095},
{"learn":[2.939358563],"iteration":236,"passed_time":0.4452833397,"remaining_time":1.433549317},
{"learn":[2.938858046],"iteration":237,"passed_time":0.446247483,"remaining_time":1.428741941},
{"learn":[2.938665176],"iteration":238,"passed_time":0.4470819221,"remaining_time":1.423553735},
{"learn":[2.936863415],"iteration":239,"passed_time":0.4480108576,"remaining_time":1.418701049},
{"learn":[2.93579721],"iteration":240,"passed_time":0.4488475023,"remaining_time":1.413590267},
{"learn":[2.932948008],"iteration":241,"passed_time":0.4497272686,"remaining_time":1.408649874},
{"learn":[2.931419094],"iteration":242,"passed_time":0.4506073197,"remaining_time":1.40374379},
{"learn":[2.928765315],"iteration":243,"passed_time":0.4515201105,"remaining_time":1.398972146},
{"learn":[2.927693384],"iteration":244,"passed_time":0.4525618636,"remaining_time":1.394629417},
{"learn":[2.927142931],"iteration":245,"passed_time":0.4534210023,"remaining_time":1.389753804},
{"learn":[2.924906872],"iteration":246,"passed_time":0.4543420351,"remaining_time":1.385099403},
{"learn":[2.923108733],"iteration":247,"passed_time":0.4554848234,"remaining_time":1.381147529},
{"learn":[2.92263089],"iteration":248,"passed_time":0.456602842,"remaining_time":1.377143511},
{"learn":[2.921987723],"iteration":249,"passed_time":0.4576578078,"remaining_time":1.372973423},
{"learn":[2.919626386],"iteration":250,"passed_time":0.4587778241,"remaining_time":1.369022272},
{"learn":[2.917007217],"iteration":251,"passed_time":0.4597715418,"remaining_time":1.364718704},
{"learn":[2.916513192],"iteration":252,"passed_time":0.4606991565,"remaining_time":1.360246126},
{"learn":[2.914615856],"iteration":253,"passed_time":0.461644293,"remaining_time":1.355852923},
{"learn":[2.91032679],"iteration":254,"passed_time":0.4625648375,"remaining_time":1.351414918},
{"learn":[2.909714257],"iteration":255,"passed_time":0.4635034345,"remaining_time":1.347056857},
{"learn":[2.908611787],"iteration":256,"passed_time":0.4644809826,"remaining_time":1.342838016},
{"learn":[2.907879949],"iteration":257,"passed_time":0.4653521361,"remaining_time":1.338338314},
{"learn":[2.90688593],"iteration":258,"passed_time":0.4662643942,"remaining_time":1.333984232},
{"learn":[2.904959356],"iteration":259,"passed_time":0.4672266766,"remaining_time":1.329799003},
{"learn":[2.901722142],"iteration":260,"passed_time":0.4682467656,"remaining_time":1.325802145},
{"learn":[2.899925795],"iteration":261,"passed_time":0.4692337981,"remaining_time":1.321734897},
{"learn":[2.899489399],"iteration":262,"passed_time":0.4700742777,"remaining_time":1.31728039},
{"learn":[2.899176927],"iteration":263,"passed_time":0.4712135198,"remaining_time":1.313686177},
{"learn":[2.893260221],"iteration":264,"passed_time":0.4723319702,"remaining_time":1.310052823},
{"learn":[2.892806573],"iteration":265,"passed_time":0.473310057,"remaining_time":1.30605106},
{"learn":[2.892247864],"iteration":266,"passed_time":0.4743756979,"remaining_time":1.302312309},
{"learn":[2.889138266],"iteration":267,"passed_time":0.4755029906,"remaining_time":1.2987619},
{"learn":[2.88399747],"iteration":268,"passed_time":0.4766321136,"remaining_time":1.29523448},
{"learn":[2.882249914],"iteration":269,"passed_time":0.4776822409,"remaining_time":1.291511244},
{"learn":[2.880334607],"iteration":270,"passed_time":0.4786802813,"remaining_time":1.28766762},
{"learn":[2.88022128],"iteration":271,"passed_time":0.4792798384,"remaining_time":1.282778391},
{"learn":[2.879638743],"iteration":272,"passed_time":0.4802841363,"remaining_time":1.278998414},
{"learn":[2.879010693],"iteration":273,"passed_time":0.4812899677,"remaining_time":1.275242761},
{"learn":[2.87786462],"iteration":274,"passed_time":0.4823219893,"remaining_time":1.271576154},
{"learn":[2.87686224],"iteration":275,"passed_time":0.4835219842,"remaining_time":1.268369263},
{"learn":[2.875588903],"iteration":276,"passed_time":0.4849660419,"remaining_time":1.265813893},
{"learn":[2.875192751],"iteration":277,"passed_time":0.4859741281,"remaining_time":1.262134246},
{"learn":[2.874637718],"iteration":278,"passed_time":0.4869239833,"remaining_time":1.258323269},
{"learn":[2.873228585],"iteration":279,"passed_time":0.4880665044,"remaining_time":1.255028154},
{"learn":[2.87276443],"iteration":280,"passed_time":0.4893664178,"remaining_time":1.252151083},
{"learn":[2.87155684],"iteration":281,"passed_time":0.4907506488,"remaining_time":1.249499879},
{"learn":[2.871166093],"iteration":282,"passed_time":0.4919896557,"remaining_time":1.246489693},
{"learn":[2.866769122],"iteration":283,"passed_time":0.4931683965,"remaining_time":1.243340042},
{"learn":[2.86634057],"iteration":284,"passed_time":0.4941794897,"remaining_time":1.239783632},
{"learn":[2.864445344],"iteration":285,"passed_time":0.4955067396,"remaining_time":1.237034308},
{"learn":[2.863860918],"iteration":286,"passed_time":0.4968762416,"remaining_time":1.234399862},
{"learn":[2.863578987],"iteration":287,"passed_time":0.4981198619,"remaining_time":1.231462992},
{"learn":[2.863223816],"iteration":288,"passed_time":0.4994218162,"remaining_time":1.228681354},
{"learn":[2.862652275],"iteration":289,"passed_time":0.500564679,"remaining_time":1.225520421},
{"learn":[2.862277695],"iteration":290,"passed_time":0.5017113894,"remaining_time":1.222382732},
{"learn":[2.860601694],"iteration":291,"passed_time":0.502947278,"remaining_time":1.219474907},
{"learn":[2.860262084],"iteration":292,"passed_time":0.5040149791,"remaining_time":1.216172663},
{"learn":[2.85466021],"iteration":293,"passed_time":0.5051482729,"remaining_time":1.213043132},
{"learn":[2.85436583],"iteration":294,"passed_time":0.5061853686,"remaining_time":1.209697237},
{"learn":[2.854127834],"iteration":295,"passed_time":0.5072275403,"remaining_time":1.206379015},
{"learn":[2.853665809],"iteration":296,"passed_time":0.5082307676,"remaining_time":1.202983938},
{"learn":[2.853427672],"iteration":297,"passed_time":0.5090307809,"remaining_time":1.199126202},
{"learn":[2.85157417],"iteration":298,"passed_time":0.5100226667,"remaining_time":1.19573876},
{"learn":[2.8488111],"iteration":299,"passed_time":0.5112064831,"remaining_time":1.192815127},
{"learn":[2.848581089],"iteration":300,"passed_time":0.5122459218,"remaining_time":1.189567772},
{"learn":[2.846384679],"iteration":301,"passed_time":0.5133206942,"remaining_time":1.186416704},
{"learn":[2.846305829],"iteration":302,"passed_time":0.5143070118,"remaining_time":1.183075865},
{"learn":[2.844900104],"iteration":303,"passed_time":0.5152457621,"remaining_time":1.179641613},
{"learn":[2.843908145],"iteration":304,"passed_time":0.5161196795,"remaining_time":1.176075991},
{"learn":[2.841072075],"iteration":305,"passed_time":0.5171117467,"remaining_time":1.172795922},
{"learn":[2.838726204],"iteration":306,"passed_time":0.5180733703,"remaining_time":1.169462038},
{"learn":[2.837688354],"iteration":307,"passed_time":0.5189252198,"remaining_time":1.165896922},
{"learn":[2.835442678],"iteration":308,"passed_time":0.5198440014,"remaining_time":1.162499045},
{"learn":[2.831472702],"iteration":309,"passed_time":0.5207479101,"remaining_time":1.159084058},
{"learn":[2.829334627],"iteration":310,"passed_time":0.5216264205,"remaining_time":1.155628951},
{"learn":[2.825625485],"iteration":311,"passed_time":0.522524274,"remaining_time":1.152233014},
{"learn":[2.825424533],"iteration":312,"passed_time":0.5233795062,"remaining_time":1.148759491},
{"learn":[2.8240624],"iteration":313,"passed_time":0.524277141,"remaining_time":1.145395283},
{"learn":[2.820169994],"iteration":314,"passed_time":0.5254317522,"remaining_time":1.142605556},
{"learn":[2.81503873],"iteration":315,"passed_time":0.5265063792,"remaining_time":1.139653049},
{"learn":[2.81481245],"iteration":316,"passed_time":0.5273494044,"remaining_time":1.136213385},
{"learn":[2.81188326],"iteration":317,"passed_time":0.5283300865,"remaining_time":1.13308528},
{"learn":[2.80812896],"iteration":318,"passed_time":0.5292449903,"remaining_time":1.129830214},
{"learn":[2.805123555],"iteration":319,"passed_time":0.5303137267,"remaining_time":1.126916669},
{"learn":[2.801258337],"iteration":320,"passed_time":0.5313887715,"remaining_time":1.124027962},
{"learn":[2.800568078],"iteration":321,"passed_time":0.5327761761,"remaining_time":1.121808222},
{"learn":[2.796185952],"iteration":322,"passed_time":0.5338912594,"remaining_time":1.119022856},
{"learn":[2.792999839],"iteration":323,"passed_time":0.5348679908,"remaining_time":1.115959141},
{"learn":[2.789579725],"iteration":324,"passed_time":0.5358921554,"remaining_time":1.113006784},
{"learn":[2.787490967],"iteration":325,"passed_time":0.5368071241,"remaining_time":1.109840496},
{"learn":[2.786790993],"iteration":326,"passed_time":0.5377621378,"remaining_time":1.106770394},
{"learn":[2.786444117],"iteration":327,"passed_time":0.5387705353,"remaining_time":1.10382256},
{"learn":[2.786168047],"iteration":328,"passed_time":0.5398550207,"remaining_time":1.101041699},
{"learn":[2.782579076],"iteration":329,"passed_time":0.5409306627,"remaining_time":1.098253164},
{"learn":[2.780391652],"iteration":330,"passed_time":0.5417398223,"remaining_time":1.094936378},
{"learn":[2.779893558],"iteration":331,"passed_time":0.5426252693,"remaining_time":1.091788193},
{"learn":[2.779665989],"iteration":332,"passed_time":0.5434571648,"remaining_time":1.088546333},
{"learn":[2.777141519],"iteration":333,"passed_time":0.5445860235,"remaining_time":1.085911053},
{"learn":[2.774997729],"iteration":334,"passed_time":0.5455198733,"remaining_time":1.082897659},
{"learn":[2.771469256],"iteration":335,"passed_time":0.5465843635,"remaining_time":1.080154814},
{"learn":[2.771249814],"iteration":336,"passed_time":0.5475762209,"remaining_time":1.077279034},
{"learn":[2.765661337],"iteration":337,"passed_time":0.5486595726,"remaining_time":1.074593601},
{"learn":[2.762822132],"iteration":338,"passed_time":0.5497561974,"remaining_time":1.0719435},
{"learn":[2.76076647],"iteration":339,"passed_time":0.5507499523,"remaining_time":1.069102849},
{"learn":[2.758532218],"iteration":340,"passed_time":0.5517422971,"remaining_time":1.066270304},
{"learn":[2.754255006],"iteration":341,"passed_time":0.5526963953,"remaining_time":1.063374936},
{"learn":[2.751293163],"iteration":342,"passed_time":0.5540197422,"remaining_time":1.061198165},
{"learn":[2.748286975],"iteration":343,"passed_time":0.5553814808,"remaining_time":1.059099568},
{"learn":[2.744056178],"iteration":344,"passed_time":0.5565864619,"remaining_time":1.056707631},
{"learn":[2.741827224],"iteration":345,"passed_time":0.5579189977,"remaining_time":1.054563655},
{"learn":[2.739140578],"iteration":346,"passed_time":0.558863082,"remaining_time":1.05169335},
{"learn":[2.734925205],"iteration":347,"passed_time":0.5597775965,"remaining_time":1.048778715},
{"learn":[2.733363258],"iteration":348,"passed_time":0.5609224938,"remaining_time":1.046305282},
{"learn":[2.732052012],"iteration":349,"passed_time":0.5620244986,"remaining_time":1.043759783},
{"learn":[2.730013751],"iteration":350,"passed_time":0.5632189096,"remaining_time":1.041393369},
{"learn":[2.729601341],"iteration":351,"passed_time":0.56436269,"remaining_time":1.038940407},
{"learn":[2.727459469],"iteration":352,"passed_time":0.565505908,"remaining_time":1.036493831},
{"learn":[2.726453925],"iteration":353,"passed_time":0.5666484703,"remaining_time":1.034053423},
{"learn":[2.722644879],"iteration":354,"passed_time":0.5677355194,"remaining_time":1.031519465},
{"learn":[2.720599295],"iteration":355,"passed_time":0.5691789996,"remaining_time":1.029638415},
{"learn":[2.718630696],"iteration":356,"passed_time":0.5703052694,"remaining_time":1.027188482},
{"learn":[2.715903463],"iteration":357,"passed_time":0.571603775,"remaining_time":1.025054814},
{"learn":[2.713144273],"iteration":358,"passed_time":0.5726852555,"remaining_time":1.022538297},
{"learn":[2.711730989],"iteration":359,"passed_time":0.5739191151,"remaining_time":1.020300649},
{"learn":[2.70940287],"iteration":360,"passed_time":0.5752981211,"remaining_time":1.018325483},
{"learn":[2.706639949],"iteration":361,"passed_time":0.576553177,"remaining_time":1.016135157},
{"learn":[2.705718002],"iteration":362,"passed_time":0.5776153996,"remaining_time":1.013611597},
{"learn":[2.702851893],"iteration":363,"passed_time":0.5786054811,"remaining_time":1.010970016},
{"learn":[2.70172306],"iteration":364,"passed_time":0.579888492,"remaining_time":1.008847102},
{"learn":[2.701423378],"iteration":365,"passed_time":0.5810404278,"remaining_time":1.006501725},
{"learn":[2.698861112],"iteration":366,"passed_time":0.5825711588,"remaining_time":1.004816195},
{"learn":[2.695420051],"iteration":367,"passed_time":0.5840877925,"remaining_time":1.003107296},
{"learn":[2.692275488],"iteration":368,"passed_time":0.5855022496,"remaining_time":1.001224714},
{"learn":[2.686827228],"iteration":369,"passed_time":0.5868657468,"remaining_time":0.9992578933},
{"learn":[2.684089653],"iteration":370,"passed_time":0.5880719159,"remaining_time":0.9970275878},
{"learn":[2.682136124],"iteration":371,"passed_time":0.5891043529,"remaining_time":0.9945094989},
{"learn":[2.681040994],"iteration":372,"passed_time":0.5902641931,"remaining_time":0.9922135363},
{"learn":[2.677842635],"iteration":373,"passed_time":0.5914068508,"remaining_time":0.9898948892},
{"learn":[2.675986593],"iteration":374,"passed_time":0.5925756827,"remaining_time":0.9876261378},
{"learn":[2.673933142],"iteration":375,"passed_time":0.5934602859,"remaining_time":0.9848915383},
{"learn":[2.672409102],"iteration":376,"passed_time":0.5946934666,"remaining_time":0.9827427844},
{"learn":[2.669051964],"iteration":377,"passed_time":0.5959926018,"remaining_time":0.980707403},
{"learn":[2.667396207],"iteration":378,"passed_time":0.5974480907,"remaining_time":0.9789320959},
{"learn":[2.662447319],"iteration":379,"passed_time":0.5987466868,"remaining_time":0.976902489},
{"learn":[2.662275115],"iteration":380,"passed_time":0.5999267253,"remaining_time":0.9746841023},
{"learn":[2.659715894],"iteration":381,"passed_time":0.6012556421,"remaining_time":0.9727120073},
{"learn":[2.655967131],"iteration":382,"passed_time":0.6024328057,"remaining_time":0.9704988019},
{"learn":[2.654292656],"iteration":383,"passed_time":0.6035817145,"remaining_time":0.968245667},
{"learn":[2.650865448],"iteration":384,"passed_time":0.6047452862,"remaining_time":0.9660216909},
{"learn":[2.649694187],"iteration":385,"passed_time":0.6055991094,"remaining_time":0.9633105004},
{"learn":[2.647155278],"iteration":386,"passed_time":0.6069175757,"remaining_time":0.9613448939},
{"learn":[2.642377866],"iteration":387,"passed_time":0.6081694184,"remaining_time":0.9592775363},
{"learn":[2.639868149],"iteration":388,"passed_time":0.6093271612,"remaining_time":0.9570665693},
{"learn":[2.639651904],"iteration":389,"passed_time":0.6112750992,"remaining_time":0.95609695},
{"learn":[2.638504933],"iteration":390,"passed_time":0.6127431055,"remaining_time":0.9543748113},
{"learn":[2.635956139],"iteration":391,"passed_time":0.6140098193,"remaining_time":0.9523417606},
{"learn":[2.633586444],"iteration":392,"passed_time":0.615132966,"remaining_time":0.9500908661},
{"learn":[2.631709201],"iteration":393,"passed_time":0.6160480257,"remaining_time":0.9475256435},
{"learn":[2.62802128],"iteration":394,"passed_time":0.6169723814,"remaining_time":0.9449830146},
{"learn":[2.623937687],"iteration":395,"passed_time":0.6178060031,"remaining_time":0.9423101664},
{"learn":[2.622416861],"iteration":396,"passed_time":0.6187712898,"remaining_time":0.9398465686},
{"learn":[2.620917933],"iteration":397,"passed_time":0.6199650247,"remaining_time":0.9377360424},
{"learn":[2.618413898],"iteration":398,"passed_time":0.6209896871,"remaining_time":0.9353754435},
{"learn":[2.615167494],"iteration":399,"passed_time":0.6220414625,"remaining_time":0.9330621937},
{"learn":[2.613754059],"iteration":400,"passed_time":0.6232059137,"remaining_time":0.9309235469},
{"learn":[2.609978848],"iteration":401,"passed_time":0.6242099016,"remaining_time":0.9285510476},
{"learn":[2.60897616],"iteration":402,"passed_time":0.6252084482,"remaining_time":0.9261772794},
{"learn":[2.607969091],"iteration":403,"passed_time":0.6262439182,"remaining_time":0.9238647903},
{"learn":[2.606531007],"iteration":404,"passed_time":0.6273718658,"remaining_time":0.9216944694},
{"learn":[2.601934424],"iteration":405,"passed_time":0.6284747044,"remaining_time":0.9194925478},
{"learn":[2.599988941],"iteration":406,"passed_time":0.6296684229,"remaining_time":0.9174284393},
{"learn":[2.598078297],"iteration":407,"passed_time":0.6306486216,"remaining_time":0.9150587843},
{"learn":[2.593981106],"iteration":408,"passed_time":0.6319502816,"remaining_time":0.9131604313},
{"learn":[2.591970695],"iteration":409,"passed_time":0.6330156249,"remaining_time":0.9109249236},
{"learn":[2.587573828],"iteration":410,"passed_time":0.6341022591,"remaining_time":0.9087256219},
{"learn":[2.585690213],"iteration":411,"passed_time":0.6350457774,"remaining_time":0.9063274688},
{"learn":[2.583282533],"iteration":412,"passed_time":0.6363798375,"remaining_time":0.9044914397},
{"learn":[2.580165234],"iteration":413,"passed_time":0.6375806742,"remaining_time":0.9024692635},
{"learn":[2.577838199],"iteration":414,"passed_time":0.6388778145,"remaining_time":0.9005867987},
{"learn":[2.574302002],"iteration":415,"passed_time":0.6402103234,"remaining_time":0.8987568001},
{"learn":[2.571088405],"iteration":416,"passed_time":0.6412620239,"remaining_time":0.8965365945},
{"learn":[2.570034277],"iteration":417,"passed_time":0.6425632313,"remaining_time":0.8946693794},
{"learn":[2.568004625],"iteration":418,"passed_time":0.6438788765,"remaining_time":0.892824886},
{"learn":[2.563902103],"iteration":419,"passed_time":0.6452525694,"remaining_time":0.891063072},
{"learn":[2.561835517],"iteration":420,"passed_time":0.646602582,"remaining_time":0.8892705343},
{"learn":[2.559887649],"iteration":421,"passed_time":0.6478595824,"remaining_time":0.8873526981},
{"learn":[2.558143189],"iteration":422,"passed_time":0.6492241457,"remaining_time":0.8855847094},
{"learn":[2.558064831],"iteration":423,"passed_time":0.6502291104,"remaining_time":0.8833301123},
{"learn":[2.555942157],"iteration":424,"passed_time":0.651377867,"remaining_time":0.8812759377},
{"learn":[2.554020956],"iteration":425,"passed_time":0.6524967896,"remaining_time":0.8791858151},
{"learn":[2.552206103],"iteration":426,"passed_time":0.6540197256,"remaining_time":0.8776423952},
{"learn":[2.552063481],"iteration":427,"passed_time":0.6552197897,"remaining_time":0.8756675695},
{"learn":[2.551533485],"iteration":428,"passed_time":0.6562431889,"remaining_time":0.8734612142},
{"learn":[2.549937972],"iteration":429,"passed_time":0.657245723,"remaining_time":0.8712327026},
{"learn":[2.547160045],"iteration":430,"passed_time":0.6582864196,"remaining_time":0.8690602616},
{"learn":[2.545645466],"iteration":431,"passed_time":0.6596017612,"remaining_time":0.8672541675},
{"learn":[2.543777331],"iteration":432,"passed_time":0.660954102,"remaining_time":0.8654987894},
{"learn":[2.541447499],"iteration":433,"passed_time":0.6622694388,"remaining_time":0.86369701},
{"learn":[2.539990782],"iteration":434,"passed_time":0.6636921555,"remaining_time":0.8620369376},
{"learn":[2.539375188],"iteration":435,"passed_time":0.6649414618,"remaining_time":0.8601536341},
{"learn":[2.53800947],"iteration":436,"passed_time":0.6662431554,"remaining_time":0.8583407243},
{"learn":[2.535149889],"iteration":437,"passed_time":0.6677300632,"remaining_time":0.856767798},
{"learn":[2.534191069],"iteration":438,"passed_time":0.6688211346,"remaining_time":0.8546894226},
{"learn":[2.532590582],"iteration":439,"passed_time":0.6702474951,"remaining_time":0.8530422665},
{"learn":[2.530995876],"iteration":440,"passed_time":0.6713035976,"remaining_time":0.8509267824},
{"learn":[2.529176068],"iteration":441,"passed_time":0.672214832,"remaining_time":0.8486332042},
{"learn":[2.528912545],"iteration":442,"passed_time":0.6734428743,"remaining_time":0.8467442008},
{"learn":[2.52741269],"iteration":443,"passed_time":0.6747794679,"remaining_time":0.8449941085},
{"learn":[2.527168354],"iteration":444,"passed_time":0.6758580007,"remaining_time":0.8429240233},
{"learn":[2.525059913],"iteration":445,"passed_time":0.6767971191,"remaining_time":0.8406852107},
{"learn":[2.52334144],"iteration":446,"passed_time":0.6776846212,"remaining_time":0.8383883569},
{"learn":[2.520547318],"iteration":447,"passed_time":0.6791548054,"remaining_time":0.8368157424},
{"learn":[2.518478135],"iteration":448,"passed_time":0.6805546878,"remaining_time":0.8351573117},
{"learn":[2.516217947],"iteration":449,"passed_time":0.682297615,"remaining_time":0.8339193073},
{"learn":[2.515126681],"iteration":450,"passed_time":0.6836848718,"remaining_time":0.8322461078},
{"learn":[2.514880876],"iteration":451,"passed_time":0.6846411847,"remaining_time":0.8300517019},
{"learn":[2.512529576],"iteration":452,"passed_time":0.6858239803,"remaining_time":0.8281362411},
{"learn":[2.509812065],"iteration":453,"passed_time":0.6872125431,"remaining_time":0.8264714726},
{"learn":[2.508193007],"iteration":454,"passed_time":0.6883536593,"remaining_time":0.824511526},
{"learn":[2.506800178],"iteration":455,"passed_time":0.6898194099,"remaining_time":0.822942454},
{"learn":[2.503630242],"iteration":456,"passed_time":0.6913049528,"remaining_time":0.8213973509},
{"learn":[2.502465574],"iteration":457,"passed_time":0.6926673374,"remaining_time":0.8197067617},
{"learn":[2.501416052],"iteration":458,"passed_time":0.6936149169,"remaining_time":0.8175286929},
{"learn":[2.501346386],"iteration":459,"passed_time":0.6948364661,"remaining_time":0.8156775907},
{"learn":[2.499846554],"iteration":460,"passed_time":0.6964401345,"remaining_time":0.8142759924},
{"learn":[2.498750793],"iteration":461,"passed_time":0.6976106317,"remaining_time":0.8123690906},
{"learn":[2.497905893],"iteration":462,"passed_time":0.6985344604,"remaining_time":0.810179277},
{"learn":[2.496190378],"iteration":463,"passed_time":0.6999940761,"remaining_time":0.8086138466},
{"learn":[2.492183488],"iteration":464,"passed_time":0.7012532593,"remaining_time":0.8068182661},
{"learn":[2.491719673],"iteration":465,"passed_time":0.7026743011,"remaining_time":0.8052104652},
{"learn":[2.490892399],"iteration":466,"passed_time":0.7040003855,"remaining_time":0.8034950867},
{"learn":[2.487360354],"iteration":467,"passed_time":0.705559685,"remaining_time":0.8020464796},
{"learn":[2.485388894],"iteration":468,"passed_time":0.7067461376,"remaining_time":0.8001752645},
{"learn":[2.482197816],"iteration":469,"passed_time":0.7081357826,"remaining_time":0.7985360953},
{"learn":[2.479714117],"iteration":470,"passed_time":0.7096431069,"remaining_time":0.7970301562},
{"learn":[2.478134619],"iteration":471,"passed_time":0.7113068651,"remaining_time":0.795699205},
{"learn":[2.474317678],"iteration":472,"passed_time":0.7128779811,"remaining_time":0.794263628},
{"learn":[2.472405844],"iteration":473,"passed_time":0.7147925943,"remaining_time":0.7932086595},
{"learn":[2.47022977],"iteration":474,"passed_time":0.7160166355,"remaining_time":0.7913868076},
{"learn":[2.469031909],"iteration":475,"passed_time":0.7174558122,"remaining_time":0.7898042974},
{"learn":[2.468246144],"iteration":476,"passed_time":0.7187934007,"remaining_time":0.7881110033},
{"learn":[2.46599075],"iteration":477,"passed_time":0.7201389553,"remaining_time":0.7864278967},
{"learn":[2.463920226],"iteration":478,"passed_time":0.7214881789,"remaining_time":0.7847501904},
{"learn":[2.461776916],"iteration":479,"passed_time":0.7228341948,"remaining_time":0.7830703777},
{"learn":[2.460470596],"iteration":480,"passed_time":0.7243231744,"remaining_time":0.781546211},
{"learn":[2.458987212],"iteration":481,"passed_time":0.725929432,"remaining_time":0.7801482277},
{"learn":[2.457017131],"iteration":482,"passed_time":0.727258106,"remaining_time":0.7784522584},
{"learn":[2.455943923],"iteration":483,"passed_time":0.7284423334,"remaining_time":0.77660381},
{"learn":[2.455313755],"iteration":484,"passed_time":0.7293209518,"remaining_time":0.774433588},
{"learn":[2.454234757],"iteration":485,"passed_time":0.7302868813,"remaining_time":0.7723610226},
{"learn":[2.45210006],"iteration":486,"passed_time":0.7314041413,"remaining_time":0.7704524117},
{"learn":[2.450598701],"iteration":487,"passed_time":0.7324510538,"remaining_time":0.7684732368},
{"learn":[2.448853848],"iteration":488,"passed_time":0.7335434332,"remaining_time":0.7665453873},
{"learn":[2.448041614],"iteration":489,"passed_time":0.7345201908,"remaining_time":0.7645006067},
{"learn":[2.447264249],"iteration":490,"passed_time":0.7355436773,"remaining_time":0.7625086186},
{"learn":[2.446214503],"iteration":491,"passed_time":0.7365378143,"remaining_time":0.7604902636},
{"learn":[2.444864417],"iteration":492,"passed_time":0.7380339838,"remaining_time":0.7589923525},
{"learn":[2.443008033],"iteration":493,"passed_time":0.7396015998,"remaining_time":0.7575676305},
{"learn":[2.44203719],"iteration":494,"passed_time":0.7413159978,"remaining_time":0.7562920786},
{"learn":[2.440179932],"iteration":495,"passed_time":0.7424647857,"remaining_time":0.7544400241},
{"learn":[2.439843932],"iteration":496,"passed_time":0.7438031175,"remaining_time":0.752782632},
{"learn":[2.438136076],"iteration":497,"passed_time":0.7447857597,"remaining_time":0.7507679746},
{"learn":[2.435915958],"iteration":498,"passed_time":0.7460796538,"remaining_time":0.749069953},
{"learn":[2.434685515],"iteration":499,"passed_time":0.7473340453,"remaining_time":0.7473340453},
{"learn":[2.434516277],"iteration":500,"passed_time":0.7484480645,"remaining_time":0.7454602479},
{"learn":[2.431811296],"iteration":501,"passed_time":0.7497784531,"remaining_time":0.7438041228},
{"learn":[2.430496321],"iteration":502,"passed_time":0.7508172257,"remaining_time":0.7418611554},
{"learn":[2.429506329],"iteration":503,"passed_time":0.7517341525,"remaining_time":0.7398018644},
{"learn":[2.428745442],"iteration":504,"passed_time":0.7529553922,"remaining_time":0.7380453844},
{"learn":[2.426934689],"iteration":505,"passed_time":0.7544859642,"remaining_time":0.7365930165},
{"learn":[2.425529804],"iteration":506,"passed_time":0.7555981575,"remaining_time":0.7347335141},
{"learn":[2.423752087],"iteration":507,"passed_time":0.7569163607,"remaining_time":0.7330764754},
{"learn":[2.421739739],"iteration":508,"passed_time":0.7578397894,"remaining_time":0.731039954},
{"learn":[2.419813426],"iteration":509,"passed_time":0.7589955692,"remaining_time":0.7292310371},
{"learn":[2.418863238],"iteration":510,"passed_time":0.7600309063,"remaining_time":0.7273094191},
{"learn":[2.417560125],"iteration":511,"passed_time":0.7611534602,"remaining_time":0.7254743917},
{"learn":[2.414939108],"iteration":512,"passed_time":0.7626740236,"remaining_time":0.7240199795},
{"learn":[2.414205759],"iteration":513,"passed_time":0.7639364032,"remaining_time":0.7223211906},
{"learn":[2.410011892],"iteration":514,"passed_time":0.7650913769,"remaining_time":0.7205229471},
{"learn":[2.407882457],"iteration":515,"passed_time":0.7660783781,"remaining_time":0.7185696415},
{"learn":[2.405321415],"iteration":516,"passed_time":0.7677099741,"remaining_time":0.7172222775},
{"learn":[2.403585375],"iteration":517,"passed_time":0.7687671903,"remaining_time":0.7153393547},
{"learn":[2.401132216],"iteration":518,"passed_time":0.770012673,"remaining_time":0.7136340958},
{"learn":[2.399571857],"iteration":519,"passed_time":0.77147232,"remaining_time":0.7121282953},
{"learn":[2.398085816],"iteration":520,"passed_time":0.7729321539,"remaining_time":0.710622844},
{"learn":[2.395029533],"iteration":521,"passed_time":0.7742708871,"remaining_time":0.7090066744},
{"learn":[2.392751907],"iteration":522,"passed_time":0.775529997,"remaining_time":0.7073189456},
{"learn":[2.392641395],"iteration":523,"passed_time":0.7767292092,"remaining_time":0.705578442},
{"learn":[2.391547546],"iteration":524,"passed_time":0.7778717075,"remaining_time":0.7037886878},
{"learn":[2.389694576],"iteration":525,"passed_time":0.7790809729,"remaining_time":0.7020615611},
{"learn":[2.389017321],"iteration":526,"passed_time":0.7802240651,"remaining_time":0.7002770072},
{"learn":[2.387436872],"iteration":527,"passed_time":0.7815281077,"remaining_time":0.6986387629},
{"learn":[2.385888362],"iteration":528,"passed_time":0.7827017585,"remaining_time":0.6968856867},
{"learn":[2.384568211],"iteration":529,"passed_time":0.7836389877,"remaining_time":0.6949251401},
{"learn":[2.384435647],"iteration":530,"passed_time":0.784657667,"remaining_time":0.6930403876},
{"learn":[2.383303499],"iteration":531,"passed_time":0.7858660168,"remaining_time":0.6913257441},
{"learn":[2.381712134],"iteration":532,"passed_time":0.7873016314,"remaining_time":0.6898121236},
{"learn":[2.380669881],"iteration":533,"passed_time":0.7884682734,"remaining_time":0.6880640738},
{"learn":[2.378953562],"iteration":534,"passed_time":0.789576484,"remaining_time":0.6862674113},
{"learn":[2.377481606],"iteration":535,"passed_time":0.7906511066,"remaining_time":0.6844442416},
{"learn":[2.375447807],"iteration":536,"passed_time":0.7917504897,"remaining_time":0.6826452081},
{"learn":[2.374045527],"iteration":537,"passed_time":0.792882355,"remaining_time":0.6808766691},
{"learn":[2.372499423],"iteration":538,"passed_time":0.7937659197,"remaining_time":0.6788981243},
{"learn":[2.369917692],"iteration":539,"passed_time":0.7947974059,"remaining_time":0.677049642},
{"learn":[2.368380715],"iteration":540,"passed_time":0.7958970981,"remaining_time":0.6752620482},
{"learn":[2.366753316],"iteration":541,"passed_time":0.7970197338,"remaining_time":0.6734963802},
{"learn":[2.365243802],"iteration":542,"passed_time":0.7981352708,"remaining_time":0.6717271064},
{"learn":[2.363556213],"iteration":543,"passed_time":0.7991331098,"remaining_time":0.6698615773},
{"learn":[2.361294504],"iteration":544,"passed_time":0.8001748825,"remaining_time":0.6680359111},
{"learn":[2.359856483],"iteration":545,"passed_time":0.8010709795,"remaining_time":0.6660919866},
{"learn":[2.358283296],"iteration":546,"passed_time":0.8018722195,"remaining_time":0.6640733372},
{"learn":[2.357003841],"iteration":547,"passed_time":0.8026217102,"remaining_time":0.6620164471},
{"learn":[2.355831833],"iteration":548,"passed_time":0.8034593213,"remaining_time":0.6600367102},
{"learn":[2.354639453],"iteration":549,"passed_time":0.8043046277,"remaining_time":0.6580674227},
{"learn":[2.35284042],"iteration":550,"passed_time":0.8052156527,"remaining_time":0.6561557678},
{"learn":[2.351635826],"iteration":551,"passed_time":0.8060749499,"remaining_time":0.6542057565},
{"learn":[2.350529788],"iteration":552,"passed_time":0.8070853852,"remaining_time":0.6523818575},
{"learn":[2.349135393],"iteration":553,"passed_time":0.8080588798,"remaining_time":0.6505311559},
{"learn":[2.34737736],"iteration":554,"passed_time":0.8090793817,"remaining_time":0.6487213061},
{"learn":[2.346303588],"iteration":555,"passed_time":0.8102153594,"remaining_time":0.64700651},
{"learn":[2.343502691],"iteration":556,"passed_time":0.8113761832,"remaining_time":0.6453135532},
{"learn":[2.340787196],"iteration":557,"passed_time":0.8124322672,"remaining_time":0.6435395378},
{"learn":[2.339552214],"iteration":558,"passed_time":0.8134891815,"remaining_time":0.6417687461},
{"learn":[2.338144335],"iteration":559,"passed_time":0.8145198979,"remaining_time":0.6399799198},
{"learn":[2.334640982],"iteration":560,"passed_time":0.8156199226,"remaining_time":0.6382480321},
{"learn":[2.332975929],"iteration":561,"passed_time":0.8167522184,"remaining_time":0.6365435439},
{"learn":[2.331750212],"iteration":562,"passed_time":0.817800461,"remaining_time":0.6347758463},
{"learn":[2.329881038],"iteration":563,"passed_time":0.8189586523,"remaining_time":0.6330956957},
{"learn":[2.327816522],"iteration":564,"passed_time":0.8200496756,"remaining_time":0.6313656795},
{"learn":[2.327683747],"iteration":565,"passed_time":0.8211063063,"remaining_time":0.6296115494},
{"learn":[2.326433694],"iteration":566,"passed_time":0.8219365666,"remaining_time":0.6276870076},
{"learn":[2.326129084],"iteration":567,"passed_time":0.8228016107,"remaining_time":0.6257927743},
{"learn":[2.324738118],"iteration":568,"passed_time":0.824332693,"remaining_time":0.624406662},
{"learn":[2.323810474],"iteration":569,"passed_time":0.8258428946,"remaining_time":0.6230042889},
{"learn":[2.323111982],"iteration":570,"passed_time":0.8270053028,"remaining_time":0.6213402362},
{"learn":[2.322044209],"iteration":571,"passed_time":0.8282663199,"remaining_time":0.6197517219},
{"learn":[2.320984502],"iteration":572,"passed_time":0.8291898995,"remaining_time":0.6179128919},
{"learn":[2.318100594],"iteration":573,"passed_time":0.8304183755,"remaining_time":0.616303533},
{"learn":[2.317435209],"iteration":574,"passed_time":0.8316163237,"remaining_time":0.6146729349},
{"learn":[2.316454925],"iteration":575,"passed_time":0.8325326566,"remaining_time":0.6128365389},
{"learn":[2.314965933],"iteration":576,"passed_time":0.8335092571,"remaining_time":0.6110475143},
{"learn":[2.313272553],"iteration":577,"passed_time":0.8345345503,"remaining_time":0.6092968516},
{"learn":[2.310673503],"iteration":578,"passed_time":0.835417775,"remaining_time":0.6074453942},
{"learn":[2.308423478],"iteration":579,"passed_time":0.8365959487,"remaining_time":0.6058108594},
{"learn":[2.307809486],"iteration":580,"passed_time":0.8376903319,"remaining_time":0.6041174683},
{"learn":[2.305403655],"iteration":581,"passed_time":0.8391869295,"remaining_time":0.6027150112},
{"learn":[2.302770482],"iteration":582,"passed_time":0.8406323096,"remaining_time":0.6012755971},
{"learn":[2.301585274],"iteration":583,"passed_time":0.8421403941,"remaining_time":0.5998808287},
{"learn":[2.299136356],"iteration":584,"passed_time":0.8435870455,"remaining_time":0.5984420921},
{"learn":[2.298505551],"iteration":585,"passed_time":0.8447209757,"remaining_time":0.5967823958},
{"learn":[2.294749255],"iteration":586,"passed_time":0.845820318,"remaining_time":0.5951001556},
{"learn":[2.294652126],"iteration":587,"passed_time":0.8468951268,"remaining_time":0.5934027079},
{"learn":[2.292605589],"iteration":588,"passed_time":0.8479844196,"remaining_time":0.5917174812},
{"learn":[2.291913858],"iteration":589,"passed_time":0.8491178352,"remaining_time":0.5900649363},
{"learn":[2.291088303],"iteration":590,"passed_time":0.8501265162,"remaining_time":0.5883278259},
{"learn":[2.290489063],"iteration":591,"passed_time":0.8511752718,"remaining_time":0.5866207954},
{"learn":[2.290095776],"iteration":592,"passed_time":0.8522103942,"remaining_time":0.584906628},
{"learn":[2.289294398],"iteration":593,"passed_time":0.8531826044,"remaining_time":0.5831517464},
{"learn":[2.287711392],"iteration":594,"passed_time":0.85412049,"remaining_time":0.5813761319},
{"learn":[2.286315243],"iteration":595,"passed_time":0.8550342797,"remaining_time":0.579586995},
{"learn":[2.285337357],"iteration":596,"passed_time":0.8560563107,"remaining_time":0.577873858},
{"learn":[2.284433572],"iteration":597,"passed_time":0.8569042605,"remaining_time":0.5760460079},
{"learn":[2.283448618],"iteration":598,"passed_time":0.8578452377,"remaining_time":0.5742837067},
{"learn":[2.282036718],"iteration":599,"passed_time":0.8587636371,"remaining_time":0.5725090914},
{"learn":[2.28079388],"iteration":600,"passed_time":0.8595514142,"remaining_time":0.5706506061},
{"learn":[2.279941093],"iteration":601,"passed_time":0.8603830197,"remaining_time":0.5688246542},
{"learn":[2.279820946],"iteration":602,"passed_time":0.8612026998,"remaining_time":0.5669941489},
{"learn":[2.277714356],"iteration":603,"passed_time":0.8622082684,"remaining_time":0.5652888647},
{"learn":[2.275293537],"iteration":604,"passed_time":0.8630755001,"remaining_time":0.5634955745},
{"learn":[2.273759365],"iteration":605,"passed_time":0.8639633659,"remaining_time":0.561718756},
{"learn":[2.272725466],"iteration":606,"passed_time":0.8647126487,"remaining_time":0.5598551416},
{"learn":[2.270911466],"iteration":607,"passed_time":0.8655369767,"remaining_time":0.5580435771},
{"learn":[2.269722986],"iteration":608,"passed_time":0.8663538376,"remaining_time":0.5562304606},
{"learn":[2.269252063],"iteration":609,"passed_time":0.8673139577,"remaining_time":0.5545122025},
{"learn":[2.268801689],"iteration":610,"passed_time":0.8682286401,"remaining_time":0.5527674975},
{"learn":[2.268346913],"iteration":611,"passed_time":0.8690695221,"remaining_time":0.5509787166},
{"learn":[2.267227663],"iteration":612,"passed_time":0.8699106645,"remaining_time":0.5491931928},
{"learn":[2.265381874],"iteration":613,"passed_time":0.8708151372,"remaining_time":0.5474505586},
{"learn":[2.265311596],"iteration":614,"passed_time":0.8717045761,"remaining_time":0.5457012387},
{"learn":[2.265170267],"iteration":615,"passed_time":0.8726278794,"remaining_time":0.5439758209},
{"learn":[2.264068429],"iteration":616,"passed_time":0.8735153782,"remaining_time":0.5422307777},
{"learn":[2.263052626],"iteration":617,"passed_time":0.8744327881,"remaining_time":0.5405069984},
{"learn":[2.260371613],"iteration":618,"passed_time":0.875260799,"remaining_time":0.5387307988},
{"learn":[2.259130779],"iteration":619,"passed_time":0.8761529666,"remaining_time":0.5369969795},
{"learn":[2.257724663],"iteration":620,"passed_time":0.8769660247,"remaining_time":0.53521759},
{"learn":[2.2562186],"iteration":621,"passed_time":0.8777618239,"remaining_time":0.533430819},
{"learn":[2.255735143],"iteration":622,"passed_time":0.878563351,"remaining_time":0.5316506956},
{"learn":[2.253457368],"iteration":623,"passed_time":0.8793336524,"remaining_time":0.5298548931},
{"learn":[2.253232008],"iteration":624,"passed_time":0.8801528583,"remaining_time":0.528091715},
{"learn":[2.252645295],"iteration":625,"passed_time":0.8811541576,"remaining_time":0.5264403433},
{"learn":[2.249573903],"iteration":626,"passed_time":0.8819505963,"remaining_time":0.5246691745},
{"learn":[2.248899345],"iteration":627,"passed_time":0.882851752,"remaining_time":0.5229631397},
{"learn":[2.2487053],"iteration":628,"passed_time":0.8836819754,"remaining_time":0.5212178265},
{"learn":[2.248260367],"iteration":629,"passed_time":0.8845115492,"remaining_time":0.5194750368},
{"learn":[2.247268484],"iteration":630,"passed_time":0.8853445233,"remaining_time":0.5177371301},
{"learn":[2.246860692],"iteration":631,"passed_time":0.8861659299,"remaining_time":0.5159953516},
{"learn":[2.246163647],"iteration":632,"passed_time":0.8870268725,"remaining_time":0.5142794032},
{"learn":[2.245110475],"iteration":633,"passed_time":0.8878913627,"remaining_time":0.5125681999},
{"learn":[2.244079766],"iteration":634,"passed_time":0.8888504984,"remaining_time":0.510914066},
{"learn":[2.242463282],"iteration":635,"passed_time":0.8897162038,"remaining_time":0.5092086449},
{"learn":[2.241834317],"iteration":636,"passed_time":0.8905528665,"remaining_time":0.5074893101},
{"learn":[2.240010825],"iteration":637,"passed_time":0.8914581173,"remaining_time":0.5058116591},
{"learn":[2.238480584],"iteration":638,"passed_time":0.8922656713,"remaining_time":0.5040812322},
{"learn":[2.238348777],"iteration":639,"passed_time":0.8932164196,"remaining_time":0.502434236},
{"learn":[2.235013995],"iteration":640,"passed_time":0.8940729198,"remaining_time":0.5007366275},
{"learn":[2.231123344],"iteration":641,"passed_time":0.8949955145,"remaining_time":0.4990784956},
{"learn":[2.230198825],"iteration":642,"passed_time":0.8960325938,"remaining_time":0.4974862146},
{"learn":[2.229279135],"iteration":643,"passed_time":0.8969716485,"remaining_time":0.4958414703},
{"learn":[2.228225762],"iteration":644,"passed_time":0.8978757908,"remaining_time":0.4941796988},
{"learn":[2.227618671],"iteration":645,"passed_time":0.8987015714,"remaining_time":0.4924773317},
{"learn":[2.225645795],"iteration":646,"passed_time":0.8998842408,"remaining_time":0.490972391},
{"learn":[2.225011688],"iteration":647,"passed_time":0.9008624445,"remaining_time":0.4893573773},
{"learn":[2.223332064],"iteration":648,"passed_time":0.9018283808,"remaining_time":0.4877376913},
{"learn":[2.222430941],"iteration":649,"passed_time":0.9027526529,"remaining_time":0.4860975823},
{"learn":[2.221312244],"iteration":650,"passed_time":0.9038187916,"remaining_time":0.484535727},
{"learn":[2.22005579],"iteration":651,"passed_time":0.9048245385,"remaining_time":0.4829431586},
{"learn":[2.219797904],"iteration":652,"passed_time":0.9058908522,"remaining_time":0.4813845723},
{"learn":[2.217460517],"iteration":653,"passed_time":0.9069858706,"remaining_time":0.4798426777},
{"learn":[2.216705286],"iteration":654,"passed_time":0.908101642,"remaining_time":0.4783130786},
{"learn":[2.216513463],"iteration":655,"passed_time":0.9091896479,"remaining_time":0.4767701812},
{"learn":[2.215651136],"iteration":656,"passed_time":0.9104585441,"remaining_time":0.475323106},
{"learn":[2.213186683],"iteration":657,"passed_time":0.9113467835,"remaining_time":0.4736787233},
{"learn":[2.212836867],"iteration":658,"passed_time":0.9123919322,"remaining_time":0.4721178283},
{"learn":[2.210549251],"iteration":659,"passed_time":0.9135498888,"remaining_time":0.4706166094},
{"learn":[2.210211097],"iteration":660,"passed_time":0.9146076994,"remaining_time":0.4690650682},
{"learn":[2.210137328],"iteration":661,"passed_time":0.9156392885,"remaining_time":0.4675016307},
{"learn":[2.208286399],"iteration":662,"passed_time":0.9167502666,"remaining_time":0.4659801506},
{"learn":[2.207303467],"iteration":663,"passed_time":0.9177171485,"remaining_time":0.4643869908},
{"learn":[2.206480305],"iteration":664,"passed_time":0.9188005193,"remaining_time":0.462854397},
{"learn":[2.20597559],"iteration":665,"passed_time":0.9199699468,"remaining_time":0.4613663097},
{"learn":[2.204600481],"iteration":666,"passed_time":0.9210229798,"remaining_time":0.4598210679},
{"learn":[2.203761437],"iteration":667,"passed_time":0.9221313815,"remaining_time":0.4583048183},
{"learn":[2.200094076],"iteration":668,"passed_time":0.9230795461,"remaining_time":0.4567105079},
{"learn":[2.19978373],"iteration":669,"passed_time":0.9241923661,"remaining_time":0.4551992251},
{"learn":[2.197171285],"iteration":670,"passed_time":0.9254103789,"remaining_time":0.4537407074},
{"learn":[2.196380317],"iteration":671,"passed_time":0.9264905285,"remaining_time":0.4522156151},
{"learn":[2.194998883],"iteration":672,"passed_time":0.9276629806,"remaining_time":0.4507366934},
{"learn":[2.193824028],"iteration":673,"passed_time":0.9288317801,"remaining_time":0.4492569144},
{"learn":[2.19348884],"iteration":674,"passed_time":0.9298843561,"remaining_time":0.4477220974},
{"learn":[2.190261559],"iteration":675,"passed_time":0.9311839271,"remaining_time":0.4463070893},
{"learn":[2.189385463],"iteration":676,"passed_time":0.9325467342,"remaining_time":0.4449225925},
{"learn":[2.188181757],"iteration":677,"passed_time":0.9338803373,"remaining_time":0.44352429},
{"learn":[2.187322914],"iteration":678,"passed_time":0.9349451952,"remaining_time":0.4419991276},
{"learn":[2.185229013],"iteration":679,"passed_time":0.9361270648,"remaining_time":0.4405303834},
{"learn":[2.184046591],"iteration":680,"passed_time":0.9374044441,"remaining_time":0.4391072212},
{"learn":[2.183808447],"iteration":681,"passed_time":0.938245341,"remaining_time":0.4374809654},
{"learn":[2.183249606],"iteration":682,"passed_time":0.9394612471,"remaining_time":0.436031062},
{"learn":[2.182111805],"iteration":683,"passed_time":0.9406860953,"remaining_time":0.4345859739},
{"learn":[2.180195403],"iteration":684,"passed_time":0.9417509857,"remaining_time":0.4330679715},
{"learn":[2.17917723],"iteration":685,"passed_time":0.942808441,"remaining_time":0.431547887},
{"learn":[2.178522522],"iteration":686,"passed_time":0.9439485015,"remaining_time":0.4300667845},
{"learn":[2.177563906],"iteration":687,"passed_time":0.9449713119,"remaining_time":0.4285335019},
{"learn":[2.176751723],"iteration":688,"passed_time":0.9460725786,"remaining_time":0.4270371146},
{"learn":[2.175144948],"iteration":689,"passed_time":0.9471838779,"remaining_time":0.4255463799},
{"learn":[2.174844712],"iteration":690,"passed_time":0.9482560562,"remaining_time":0.4240392495},
{"learn":[2.172675205],"iteration":691,"passed_time":0.9491282386,"remaining_time":0.4224443605},
{"learn":[2.170430855],"iteration":692,"passed_time":0.9501223976,"remaining_time":0.4209055932},
{"learn":[2.169073077],"iteration":693,"passed_time":0.9513086784,"remaining_time":0.419453106},
{"learn":[2.167006327],"iteration":694,"passed_time":0.952442986,"remaining_time":0.4179785766},
{"learn":[2.166186938],"iteration":695,"passed_time":0.9538332241,"remaining_time":0.4166168105},
{"learn":[2.165144567],"iteration":696,"passed_time":0.9549776973,"remaining_time":0.4151481238},
{"learn":[2.163409693],"iteration":697,"passed_time":0.9560690174,"remaining_time":0.4136573686},
{"learn":[2.162694931],"iteration":698,"passed_time":0.95718766,"remaining_time":0.4121795217},
{"learn":[2.160063675],"iteration":699,"passed_time":0.9580866706,"remaining_time":0.4106085731},
{"learn":[2.159090008],"iteration":700,"passed_time":0.9589333656,"remaining_time":0.4090172273},
{"learn":[2.157784136],"iteration":701,"passed_time":0.9598466021,"remaining_time":0.4074562499},
{"learn":[2.155613807],"iteration":702,"passed_time":0.9609054633,"remaining_time":0.4059586381},
{"learn":[2.154287667],"iteration":703,"passed_time":0.961762438,"remaining_time":0.4043773887},
{"learn":[2.153143583],"iteration":704,"passed_time":0.9628020184,"remaining_time":0.4028746035},
{"learn":[2.152929339],"iteration":705,"passed_time":0.9637269285,"remaining_time":0.4013253782},
{"learn":[2.150931896],"iteration":706,"passed_time":0.9647005661,"remaining_time":0.399798113},
{"learn":[2.149757234],"iteration":707,"passed_time":0.9658295758,"remaining_time":0.3983364917},
{"learn":[2.147603953],"iteration":708,"passed_time":0.9669043998,"remaining_time":0.3968535689},
{"learn":[2.14499299],"iteration":709,"passed_time":0.9680802062,"remaining_time":0.395413042},
{"learn":[2.144209419],"iteration":710,"passed_time":0.9694766698,"remaining_time":0.3940629502},
{"learn":[2.143827666],"iteration":711,"passed_time":0.9710003411,"remaining_time":0.3927641829},
{"learn":[2.143402147],"iteration":712,"passed_time":0.9724405976,"remaining_time":0.3914312083},
{"learn":[2.141186558],"iteration":713,"passed_time":0.9734171261,"remaining_time":0.3899121821},
{"learn":[2.140883692],"iteration":714,"passed_time":0.9745029901,"remaining_time":0.3884382548},
{"learn":[2.14057542],"iteration":715,"passed_time":0.9757566667,"remaining_time":0.3870319739},
{"learn":[2.137939701],"iteration":716,"passed_time":0.9769444866,"remaining_time":0.3856001251},
{"learn":[2.135917036],"iteration":717,"passed_time":0.9781500397,"remaining_time":0.3841759209},
{"learn":[2.135452776],"iteration":718,"passed_time":0.9792240659,"remaining_time":0.3827009215},
{"learn":[2.133751178],"iteration":719,"passed_time":0.9804293667,"remaining_time":0.381278087},
{"learn":[2.131659055],"iteration":720,"passed_time":0.9818079105,"remaining_time":0.3799228946},
{"learn":[2.130585943],"iteration":721,"passed_time":0.9829777068,"remaining_time":0.3784872611},
{"learn":[2.127789902],"iteration":722,"passed_time":0.9842510278,"remaining_time":0.3770920259},
{"learn":[2.125277424],"iteration":723,"passed_time":0.9852505505,"remaining_time":0.3755927513},
{"learn":[2.123755519],"iteration":724,"passed_time":0.9865130855,"remaining_time":0.3741946186},
{"learn":[2.123299002],"iteration":725,"passed_time":0.9877413905,"remaining_time":0.3727839408},
{"learn":[2.122899067],"iteration":726,"passed_time":0.9889326835,"remaining_time":0.371359866},
{"learn":[2.121583499],"iteration":727,"passed_time":0.9901448898,"remaining_time":0.3699442445},
{"learn":[2.121486341],"iteration":728,"passed_time":0.9912026908,"remaining_time":0.3684717822},
{"learn":[2.120830511],"iteration":729,"passed_time":0.9923251915,"remaining_time":0.3670243859},
{"learn":[2.120058003],"iteration":730,"passed_time":0.9936704084,"remaining_time":0.3656598357},
{"learn":[2.118735907],"iteration":731,"passed_time":0.9948292774,"remaining_time":0.3642271125},
{"learn":[2.117262921],"iteration":732,"passed_time":0.9961188457,"remaining_time":0.3628427446},
{"learn":[2.115429846],"iteration":733,"passed_time":0.9972732177,"remaining_time":0.3614096402},
{"learn":[2.112539871],"iteration":734,"passed_time":0.9984489227,"remaining_time":0.3599849858},
{"learn":[2.111856995],"iteration":735,"passed_time":0.9996373622,"remaining_time":0.3585655756},
{"learn":[2.110092868],"iteration":736,"passed_time":1.00053199,"remaining_time":0.3570419449},
{"learn":[2.109418148],"iteration":737,"passed_time":1.001392738,"remaining_time":0.3555079911},
{"learn":[2.108453171],"iteration":738,"passed_time":1.002207511,"remaining_time":0.3539596218},
{"learn":[2.108246446],"iteration":739,"passed_time":1.003110778,"remaining_time":0.3524443275},
{"learn":[2.10751965],"iteration":740,"passed_time":1.004026986,"remaining_time":0.3509352083},
{"learn":[2.10581924],"iteration":741,"passed_time":1.004972457,"remaining_time":0.3494378623},
{"learn":[2.104941236],"iteration":742,"passed_time":1.006067017,"remaining_time":0.3479935712},
{"learn":[2.104023628],"iteration":743,"passed_time":1.006955513,"remaining_time":0.3464793161},
{"learn":[2.102344745],"iteration":744,"passed_time":1.007811133,"remaining_time":0.3449554884},
{"learn":[2.101794975],"iteration":745,"passed_time":1.009014476,"remaining_time":0.3435518458},
{"learn":[2.101462591],"iteration":746,"passed_time":1.010176102,"remaining_time":0.3421346103},
{"learn":[2.10008412],"iteration":747,"passed_time":1.01131493,"remaining_time":0.3407103776},
{"learn":[2.099945017],"iteration":748,"passed_time":1.012555211,"remaining_time":0.3393209051},
{"learn":[2.097944606],"iteration":749,"passed_time":1.013681172,"remaining_time":0.337893724},
{"learn":[2.096266193],"iteration":750,"passed_time":1.014676661,"remaining_time":0.336424086},
{"learn":[2.095971668],"iteration":751,"passed_time":1.015736649,"remaining_time":0.3349769799},
{"learn":[2.093435228],"iteration":752,"passed_time":1.016685057,"remaining_time":0.3334943014},
{"learn":[2.09117192],"iteration":753,"passed_time":1.017620057,"remaining_time":0.3320086659},
{"learn":[2.090896783],"iteration":754,"passed_time":1.018794218,"remaining_time":0.3306020974},
{"learn":[2.088251012],"iteration":755,"passed_time":1.019956938,"remaining_time":0.329192451},
{"learn":[2.086418577],"iteration":756,"passed_time":1.021051929,"remaining_time":0.3277617155},
{"learn":[2.083917088],"iteration":757,"passed_time":1.022163708,"remaining_time":0.3263372262},
{"learn":[2.082235882],"iteration":758,"passed_time":1.023092846,"remaining_time":0.3248555675},
{"learn":[2.081184513],"iteration":759,"passed_time":1.024003983,"remaining_time":0.3233696787},
{"learn":[2.079150689],"iteration":760,"passed_time":1.025052645,"remaining_time":0.3219284918},
{"learn":[2.077480452],"iteration":761,"passed_time":1.02596474,"remaining_time":0.3204456798},
{"learn":[2.075840576],"iteration":762,"passed_time":1.027022322,"remaining_time":0.3190095548},
{"learn":[2.074019598],"iteration":763,"passed_time":1.028004266,"remaining_time":0.317551056},
{"learn":[2.072804877],"iteration":764,"passed_time":1.028959157,"remaining_time":0.3160854926},
{"learn":[2.071132966],"iteration":765,"passed_time":1.029918988,"remaining_time":0.3146227718},
{"learn":[2.07011472],"iteration":766,"passed_time":1.030911585,"remaining_time":0.313171316},
{"learn":[2.068775052],"iteration":767,"passed_time":1.031890417,"remaining_time":0.3117168967},
{"learn":[2.066257256],"iteration":768,"passed_time":1.032946071,"remaining_time":0.3102867911},
{"learn":[2.065750983],"iteration":769,"passed_time":1.033963798,"remaining_time":0.3088463294},
{"learn":[2.065645609],"iteration":770,"passed_time":1.035087663,"remaining_time":0.3074384887},
{"learn":[2.063378481],"iteration":771,"passed_time":1.035921353,"remaining_time":0.3059456846},
{"learn":[2.061295004],"iteration":772,"passed_time":1.036990978,"remaining_time":0.3045238707},
{"learn":[2.060206368],"iteration":773,"passed_time":1.038320363,"remaining_time":0.3031788139},
{"learn":[2.058874225],"iteration":774,"passed_time":1.039355134,"remaining_time":0.3017482647},
{"learn":[2.058261749],"iteration":775,"passed_time":1.040223833,"remaining_time":0.3002707973},
{"learn":[2.055088508],"iteration":776,"passed_time":1.041285738,"remaining_time":0.2988503469},
{"learn":[2.053660174],"iteration":777,"passed_time":1.042378604,"remaining_time":0.2974396532},
{"learn":[2.052723196],"iteration":778,"passed_time":1.043671891,"remaining_time":0.2960866339},
{"learn":[2.051213287],"iteration":779,"passed_time":1.044873407,"remaining_time":0.2947078839},
{"learn":[2.050350738],"iteration":780,"passed_time":1.045849288,"remaining_time":0.2932663177},
{"learn":[2.049623484],"iteration":781,"passed_time":1.046949704,"remaining_time":0.2918606592},
{"learn":[2.04665145],"iteration":782,"passed_time":1.048020588,"remaining_time":0.2904475959},
{"learn":[2.045132408],"iteration":783,"passed_time":1.048987047,"remaining_time":0.2890066354},
{"learn":[2.043920752],"iteration":784,"passed_time":1.050155056,"remaining_time":0.2876220854},
{"learn":[2.043293396],"iteration":785,"passed_time":1.051094011,"remaining_time":0.2861757232},
{"learn":[2.042496902],"iteration":786,"passed_time":1.052051358,"remaining_time":0.2847356279},
{"learn":[2.040784772],"iteration":787,"passed_time":1.053226464,"remaining_time":0.2833553432},
{"learn":[2.038958343],"iteration":788,"passed_time":1.054359815,"remaining_time":0.2819644119},
{"learn":[2.037548575],"iteration":789,"passed_time":1.055495437,"remaining_time":0.2805747365},
{"learn":[2.037435102],"iteration":790,"passed_time":1.056716407,"remaining_time":0.2792082543},
{"learn":[2.035946284],"iteration":791,"passed_time":1.057625681,"remaining_time":0.27776028},
{"learn":[2.035312813],"iteration":792,"passed_time":1.058794508,"remaining_time":0.2763814164},
{"learn":[2.034940057],"iteration":793,"passed_time":1.059926417,"remaining_time":0.2749935038},
{"learn":[2.03441424],"iteration":794,"passed_time":1.06108724,"remaining_time":0.2736136907},
{"learn":[2.032673108],"iteration":795,"passed_time":1.061998273,"remaining_time":0.2721704116},
{"learn":[2.031337604],"iteration":796,"passed_time":1.062928116,"remaining_time":0.2707332591},
{"learn":[2.03012815],"iteration":797,"passed_time":1.063780936,"remaining_time":0.2692778811},
{"learn":[2.029681563],"iteration":798,"passed_time":1.064631019,"remaining_time":0.2678233228},
{"learn":[2.029504908],"iteration":799,"passed_time":1.065592624,"remaining_time":0.266398156},
{"learn":[2.028686585],"iteration":800,"passed_time":1.06675851,"remaining_time":0.2650248981},
{"learn":[2.028621268],"iteration":801,"passed_time":1.068051992,"remaining_time":0.2636836589},
{"learn":[2.026697215],"iteration":802,"passed_time":1.069070686,"remaining_time":0.2622751247},
{"learn":[2.025726371],"iteration":803,"passed_time":1.069928625,"remaining_time":0.2608283712},
{"learn":[2.025555277],"iteration":804,"passed_time":1.070814269,"remaining_time":0.2593897919},
{"learn":[2.024128394],"iteration":805,"passed_time":1.071729415,"remaining_time":0.2579596854},
{"learn":[2.023810383],"iteration":806,"passed_time":1.072568239,"remaining_time":0.2565126024},
{"learn":[2.023147342],"iteration":807,"passed_time":1.07351097,"remaining_time":0.2550917156},
{"learn":[2.022234048],"iteration":808,"passed_time":1.074481303,"remaining_time":0.2536785276},
{"learn":[2.021089326],"iteration":809,"passed_time":1.075296465,"remaining_time":0.2522300351},
{"learn":[2.018766943],"iteration":810,"passed_time":1.076108336,"remaining_time":0.2507823373},
{"learn":[2.017189739],"iteration":811,"passed_time":1.076916407,"remaining_time":0.2493353257},
{"learn":[2.015689176],"iteration":812,"passed_time":1.077839333,"remaining_time":0.2479163042},
{"learn":[2.013913966],"iteration":813,"passed_time":1.078616263,"remaining_time":0.2464651413},
{"learn":[2.012288971],"iteration":814,"passed_time":1.079460184,"remaining_time":0.2450308393},
{"learn":[2.010420726],"iteration":815,"passed_time":1.08028712,"remaining_time":0.2435941545},
{"learn":[2.008338388],"iteration":816,"passed_time":1.081235514,"remaining_time":0.2421861678},
{"learn":[2.006905332],"iteration":817,"passed_time":1.082094281,"remaining_time":0.2407593631},
{"learn":[2.004722419],"iteration":818,"passed_time":1.082884597,"remaining_time":0.2393188182},
{"learn":[2.004662973],"iteration":819,"passed_time":1.083672437,"remaining_time":0.2378793154},
{"learn":[2.00306162],"iteration":820,"passed_time":1.084519286,"remaining_time":0.2364542657},
{"learn":[2.001497473],"iteration":821,"passed_time":1.085416416,"remaining_time":0.2350415109},
{"learn":[1.999587371],"iteration":822,"passed_time":1.08639814,"remaining_time":0.2336482026},
{"learn":[1.999442222],"iteration":823,"passed_time":1.087230617,"remaining_time":0.2322240153},
{"learn":[1.998040328],"iteration":824,"passed_time":1.088072052,"remaining_time":0.2308031625},
{"learn":[1.997889316],"iteration":825,"passed_time":1.088911516,"remaining_time":0.2293832975},
{"learn":[1.996658768],"iteration":826,"passed_time":1.089835832,"remaining_time":0.2279825864},
{"learn":[1.995741719],"iteration":827,"passed_time":1.090727344,"remaining_time":0.2265762115},
{"learn":[1.994826922],"iteration":828,"passed_time":1.091582099,"remaining_time":0.225163497},
{"learn":[1.993638444],"iteration":829,"passed_time":1.092562468,"remaining_time":0.223777855},
{"learn":[1.992585617],"iteration":830,"passed_time":1.09356663,"remaining_time":0.222398027},
{"learn":[1.990974559],"iteration":831,"passed_time":1.094607752,"remaining_time":0.2210265654},
{"learn":[1.990873006],"iteration":832,"passed_time":1.09576588,"remaining_time":0.2196793541},
{"learn":[1.990669884],"iteration":833,"passed_time":1.096856921,"remaining_time":0.2183192433},
{"learn":[1.989409618],"iteration":834,"passed_time":1.09795482,"remaining_time":0.2169611321},
{"learn":[1.987396151],"iteration":835,"passed_time":1.099181899,"remaining_time":0.2156289849},
{"learn":[1.985722265],"iteration":836,"passed_time":1.100109264,"remaining_time":0.2142387217},
{"learn":[1.983401909],"iteration":837,"passed_time":1.101073898,"remaining_time":0.2128567679},
{"learn":[1.981728347],"iteration":838,"passed_time":1.10209957,"remaining_time":0.2114875218},
{"learn":[1.979737547],"iteration":839,"passed_time":1.103106296,"remaining_time":0.210115485},
{"learn":[1.979691782],"iteration":840,"passed_time":1.104144816,"remaining_time":0.2087503278},
{"learn":[1.979157335],"iteration":841,"passed_time":1.105125541,"remaining_time":0.2073751015},
{"learn":[1.978397207],"iteration":842,"passed_time":1.10609068,"remaining_time":0.2059979084},
{"learn":[1.976838011],"iteration":843,"passed_time":1.106978521,"remaining_time":0.2046074044},
{"learn":[1.975799352],"iteration":844,"passed_time":1.107864674,"remaining_time":0.2032177805},
{"learn":[1.975377292],"iteration":845,"passed_time":1.109116655,"remaining_time":0.2018959396},
{"learn":[1.975313406],"iteration":846,"passed_time":1.10999246,"remaining_time":0.2005063121},
{"learn":[1.97365799],"iteration":847,"passed_time":1.110934618,"remaining_time":0.19912979},
{"learn":[1.97210601],"iteration":848,"passed_time":1.111901456,"remaining_time":0.1977586807},
{"learn":[1.971259523],"iteration":849,"passed_time":1.112791497,"remaining_time":0.19637497},
{"learn":[1.970026889],"iteration":850,"passed_time":1.113760994,"remaining_time":0.1950063315},
{"learn":[1.969829309],"iteration":851,"passed_time":1.114696019,"remaining_time":0.1936326418},
{"learn":[1.968112976],"iteration":852,"passed_time":1.115635038,"remaining_time":0.1922606689},
{"learn":[1.967642504],"iteration":853,"passed_time":1.116614175,"remaining_time":0.1908965685},
{"learn":[1.966089369],"iteration":854,"passed_time":1.117614983,"remaining_time":0.1895370439},
{"learn":[1.965025181],"iteration":855,"passed_time":1.118659175,"remaining_time":0.1881856556},
{"learn":[1.96497171],"iteration":856,"passed_time":1.119690008,"remaining_time":0.1868327552},
{"learn":[1.963853781],"iteration":857,"passed_time":1.120526929,"remaining_time":0.1854485128},
{"learn":[1.963332092],"iteration":858,"passed_time":1.121293307,"remaining_time":0.1840539655},
{"learn":[1.963026622],"iteration":859,"passed_time":1.122137116,"remaining_time":0.182673484},
{"learn":[1.961335286],"iteration":860,"passed_time":1.123242497,"remaining_time":0.1813364775},
{"learn":[1.959349037],"iteration":861,"passed_time":1.124248379,"remaining_time":0.1799840793},
{"learn":[1.958235182],"iteration":862,"passed_time":1.125144489,"remaining_time":0.178615058},
{"learn":[1.957717896],"iteration":863,"passed_time":1.126076446,"remaining_time":0.1772527739},
{"learn":[1.957301348],"iteration":864,"passed_time":1.126890644,"remaining_time":0.1758731063},
{"learn":[1.956074625],"iteration":865,"passed_time":1.127814618,"remaining_time":0.1745117308},
{"learn":[1.955632311],"iteration":866,"passed_time":1.128654578,"remaining_time":0.1731384762},
{"learn":[1.955070194],"iteration":867,"passed_time":1.129541856,"remaining_time":0.1717736462},
{"learn":[1.95433336],"iteration":868,"passed_time":1.130451504,"remaining_time":0.1704132877},
{"learn":[1.954045752],"iteration":869,"passed_time":1.131368905,"remaining_time":0.1690551237},
{"learn":[1.952686501],"iteration":870,"passed_time":1.132493829,"remaining_time":0.1677287072},
{"learn":[1.95080129],"iteration":871,"passed_time":1.133543394,"remaining_time":0.1663916909},
{"learn":[1.949944261],"iteration":872,"passed_time":1.134626528,"remaining_time":0.1650602165},
{"learn":[1.949185807],"iteration":873,"passed_time":1.13573055,"remaining_time":0.1637323219},
{"learn":[1.948571373],"iteration":874,"passed_time":1.136751206,"remaining_time":0.1623930294},
{"learn":[1.945270303],"iteration":875,"passed_time":1.137858063,"remaining_time":0.1610666665},
{"learn":[1.944445416],"iteration":876,"passed_time":1.139109326,"remaining_time":0.1597610571},
{"learn":[1.942107255],"iteration":877,"passed_time":1.140561603,"remaining_time":0.1584835029},
{"learn":[1.941704288],"iteration":878,"passed_time":1.141691496,"remaining_time":0.1571611729},
{"learn":[1.940472404],"iteration":879,"passed_time":1.142771341,"remaining_time":0.1558324556},
{"learn":[1.939302574],"iteration":880,"passed_time":1.1440324,"remaining_time":0.1545287804},
{"learn":[1.938430494],"iteration":881,"passed_time":1.14498048,"remaining_time":0.1531833295},
{"learn":[1.93826348],"iteration":882,"passed_time":1.146089819,"remaining_time":0.1518601459},
{"learn":[1.937733388],"iteration":883,"passed_time":1.147253118,"remaining_time":0.1505445268},
{"learn":[1.936473576],"iteration":884,"passed_time":1.148323354,"remaining_time":0.149217159},
{"learn":[1.935753961],"iteration":885,"passed_time":1.1495969,"remaining_time":0.1479165312},
{"learn":[1.934184993],"iteration":886,"passed_time":1.150841085,"remaining_time":0.1466122239},
{"learn":[1.932146837],"iteration":887,"passed_time":1.152638096,"remaining_time":0.1453777779},
{"learn":[1.931879159],"iteration":888,"passed_time":1.153881703,"remaining_time":0.1440729685},
{"learn":[1.931445026],"iteration":889,"passed_time":1.155020034,"remaining_time":0.1427552851},
{"learn":[1.930460652],"iteration":890,"passed_time":1.156312635,"remaining_time":0.1414568768},
{"learn":[1.928559176],"iteration":891,"passed_time":1.157501913,"remaining_time":0.1401459715},
{"learn":[1.928434109],"iteration":892,"passed_time":1.158361848,"remaining_time":0.1387958765},
{"learn":[1.927208642],"iteration":893,"passed_time":1.159489898,"remaining_time":0.137478668},
{"learn":[1.92662515],"iteration":894,"passed_time":1.160605096,"remaining_time":0.1361603744},
{"learn":[1.92454884],"iteration":895,"passed_time":1.1617142,"remaining_time":0.1348418268},
{"learn":[1.924071078],"iteration":896,"passed_time":1.162819182,"remaining_time":0.1335232728},
{"learn":[1.923067131],"iteration":897,"passed_time":1.163753436,"remaining_time":0.1321858023},
{"learn":[1.920922142],"iteration":898,"passed_time":1.164843299,"remaining_time":0.1308667111},
{"learn":[1.920305454],"iteration":899,"passed_time":1.165945104,"remaining_time":0.129549456},
{"learn":[1.919663443],"iteration":900,"passed_time":1.167382372,"remaining_time":0.1282695392},
{"learn":[1.91659438],"iteration":901,"passed_time":1.168739653,"remaining_time":0.1269805831},
{"learn":[1.915284824],"iteration":902,"passed_time":1.170024154,"remaining_time":0.1256836577},
{"learn":[1.913834827],"iteration":903,"passed_time":1.17101042,"remaining_time":0.1243550888},
{"learn":[1.913273664],"iteration":904,"passed_time":1.171966082,"remaining_time":0.1230240639},
{"learn":[1.912256716],"iteration":905,"passed_time":1.172821751,"remaining_time":0.1216834929},
{"learn":[1.912078728],"iteration":906,"passed_time":1.173864877,"remaining_time":0.1203632123},
{"learn":[1.910620097],"iteration":907,"passed_time":1.1750477,"remaining_time":0.1190576965},
{"learn":[1.909334569],"iteration":908,"passed_time":1.176157757,"remaining_time":0.1177451659},
{"learn":[1.908584532],"iteration":909,"passed_time":1.177187433,"remaining_time":0.1164251308},
{"learn":[1.90796911],"iteration":910,"passed_time":1.178212107,"remaining_time":0.1151052442},
{"learn":[1.906425583],"iteration":911,"passed_time":1.179212411,"remaining_time":0.1137836537},
{"learn":[1.905805561],"iteration":912,"passed_time":1.18000342,"remaining_time":0.1124428231},
{"learn":[1.90490376],"iteration":913,"passed_time":1.18098949,"remaining_time":0.1111215494},
{"learn":[1.904296357],"iteration":914,"passed_time":1.182300366,"remaining_time":0.1098311815},
{"learn":[1.903109983],"iteration":915,"passed_time":1.183254938,"remaining_time":0.1085080947},
{"learn":[1.902189397],"iteration":916,"passed_time":1.184214966,"remaining_time":0.1071863055},
{"learn":[1.900387618],"iteration":917,"passed_time":1.185112362,"remaining_time":0.1058597099},
{"learn":[1.898420104],"iteration":918,"passed_time":1.185973556,"remaining_time":0.1045308575},
{"learn":[1.898046831],"iteration":919,"passed_time":1.186952961,"remaining_time":0.1032133009},
{"learn":[1.897962984],"iteration":920,"passed_time":1.187967087,"remaining_time":0.1018994569},
{"learn":[1.89775404],"iteration":921,"passed_time":1.18905569,"remaining_time":0.1005925638},
{"learn":[1.897125545],"iteration":922,"passed_time":1.190139608,"remaining_time":0.09928575281},
{"learn":[1.895145632],"iteration":923,"passed_time":1.191066835,"remaining_time":0.09796653618},
{"learn":[1.893310901],"iteration":924,"passed_time":1.191902502,"remaining_time":0.09664074338},
{"learn":[1.891831829],"iteration":925,"passed_time":1.19290421,"remaining_time":0.09532927811},
{"learn":[1.89074853],"iteration":926,"passed_time":1.193927428,"remaining_time":0.09402017499},
{"learn":[1.889612084],"iteration":927,"passed_time":1.195060306,"remaining_time":0.09272019614},
{"learn":[1.887566493],"iteration":928,"passed_time":1.196283365,"remaining_time":0.09142746923},
{"learn":[1.886753119],"iteration":929,"passed_time":1.197431282,"remaining_time":0.09012923629},
{"learn":[1.88527277],"iteration":930,"passed_time":1.198392323,"remaining_time":0.08881747614},
{"learn":[1.885030363],"iteration":931,"passed_time":1.199453987,"remaining_time":0.0875138102},
{"learn":[1.883721886],"iteration":932,"passed_time":1.20057237,"remaining_time":0.0862147361},
{"learn":[1.882803352],"iteration":933,"passed_time":1.201620166,"remaining_time":0.084911061},
{"learn":[1.881921267],"iteration":934,"passed_time":1.202708298,"remaining_time":0.08361073729},
{"learn":[1.881671793],"iteration":935,"passed_time":1.203774331,"remaining_time":0.08230935599},
{"learn":[1.881196707],"iteration":936,"passed_time":1.204860602,"remaining_time":0.08100983769},
{"learn":[1.879808297],"iteration":937,"passed_time":1.205715546,"remaining_time":0.07969548386},
{"learn":[1.878552205],"iteration":938,"passed_time":1.206843184,"remaining_time":0.07839982343},
{"learn":[1.877582966],"iteration":939,"passed_time":1.207916558,"remaining_time":0.07710105691},
{"learn":[1.876727787],"iteration":940,"passed_time":1.20899607,"remaining_time":0.07580315422},
{"learn":[1.876032425],"iteration":941,"passed_time":1.210464676,"remaining_time":0.07452967218},
{"learn":[1.875234873],"iteration":942,"passed_time":1.211738155,"remaining_time":0.07324398182},
{"learn":[1.872802508],"iteration":943,"passed_time":1.213012854,"remaining_time":0.07195838962},
{"learn":[1.871733352],"iteration":944,"passed_time":1.213919703,"remaining_time":0.07065141131},
{"learn":[1.871036805],"iteration":945,"passed_time":1.215124044,"remaining_time":0.06936226045},
{"learn":[1.870912165],"iteration":946,"passed_time":1.216238578,"remaining_time":0.06806826257},
{"learn":[1.870044471],"iteration":947,"passed_time":1.217332241,"remaining_time":0.06677349847},
{"learn":[1.868693353],"iteration":948,"passed_time":1.21836693,"remaining_time":0.06547598886},
{"learn":[1.866382254],"iteration":949,"passed_time":1.219508705,"remaining_time":0.06418466868},
{"learn":[1.866096284],"iteration":950,"passed_time":1.220499261,"remaining_time":0.0628858715},
{"learn":[1.865941783],"iteration":951,"passed_time":1.221512192,"remaining_time":0.06158884999},
{"learn":[1.865769641],"iteration":952,"passed_time":1.222527227,"remaining_time":0.06029252851},
{"learn":[1.863936497],"iteration":953,"passed_time":1.22359059,"remaining_time":0.05899912699},
{"learn":[1.863147926],"iteration":954,"passed_time":1.225000553,"remaining_time":0.05772253914},
{"learn":[1.8628144],"iteration":955,"passed_time":1.226235471,"remaining_time":0.0564376158},
{"learn":[1.861975508],"iteration":956,"passed_time":1.227712376,"remaining_time":0.05516367},
{"learn":[1.861577998],"iteration":957,"passed_time":1.228756601,"remaining_time":0.05387033116},
{"learn":[1.859941285],"iteration":958,"passed_time":1.229807073,"remaining_time":0.05257777894},
{"learn":[1.858669455],"iteration":959,"passed_time":1.230839918,"remaining_time":0.05128499658},
{"learn":[1.8585587],"iteration":960,"passed_time":1.231995881,"remaining_time":0.04999775169},
{"learn":[1.856799328],"iteration":961,"passed_time":1.232830023,"remaining_time":0.04869806745},
{"learn":[1.855965189],"iteration":962,"passed_time":1.233884866,"remaining_time":0.04740782975},
{"learn":[1.855560597],"iteration":963,"passed_time":1.234736866,"remaining_time":0.04611050538},
{"learn":[1.854547871],"iteration":964,"passed_time":1.23574701,"remaining_time":0.04481983975},
{"learn":[1.854291499],"iteration":965,"passed_time":1.236734803,"remaining_time":0.04352896823},
{"learn":[1.854217209],"iteration":966,"passed_time":1.2377059,"remaining_time":0.04223815378},
{"learn":[1.852867459],"iteration":967,"passed_time":1.238901261,"remaining_time":0.04095541359},
{"learn":[1.852742446],"iteration":968,"passed_time":1.239906706,"remaining_time":0.039666778},
{"learn":[1.851369567],"iteration":969,"passed_time":1.2408135,"remaining_time":0.03837567525},
{"learn":[1.851036314],"iteration":970,"passed_time":1.241897456,"remaining_time":0.03709065521},
{"learn":[1.850803935],"iteration":971,"passed_time":1.242786483,"remaining_time":0.03580043366},
{"learn":[1.849954005],"iteration":972,"passed_time":1.243680608,"remaining_time":0.03451117822},
{"learn":[1.849387225],"iteration":973,"passed_time":1.244841695,"remaining_time":0.03322986044},
{"learn":[1.848777731],"iteration":974,"passed_time":1.245981609,"remaining_time":0.03194824639},
{"learn":[1.84725807],"iteration":975,"passed_time":1.247051106,"remaining_time":0.03066519113},
{"learn":[1.846356941],"iteration":976,"passed_time":1.248322608,"remaining_time":0.02938732854},
{"learn":[1.844804994],"iteration":977,"passed_time":1.249230653,"remaining_time":0.02810130303},
{"learn":[1.843137243],"iteration":978,"passed_time":1.250161007,"remaining_time":0.02681652824},
{"learn":[1.841468533],"iteration":979,"passed_time":1.25105733,"remaining_time":0.02553178225},
{"learn":[1.840363674],"iteration":980,"passed_time":1.252032004,"remaining_time":0.02424934563},
{"learn":[1.839167362],"iteration":981,"passed_time":1.253449707,"remaining_time":0.02297565655},
{"learn":[1.839109082],"iteration":982,"passed_time":1.254580588,"remaining_time":0.02169671413},
{"learn":[1.837530295],"iteration":983,"passed_time":1.255780792,"remaining_time":0.02041919988},
{"learn":[1.837261646],"iteration":984,"passed_time":1.25711506,"remaining_time":0.01914388416},
{"learn":[1.836581436],"iteration":985,"passed_time":1.257991772,"remaining_time":0.01786195214},
{"learn":[1.835481881],"iteration":986,"passed_time":1.258961635,"remaining_time":0.01658206814},
{"learn":[1.834178221],"iteration":987,"passed_time":1.25987967,"remaining_time":0.01530218222},
{"learn":[1.833564691],"iteration":988,"passed_time":1.260695252,"remaining_time":0.01402188855},
{"learn":[1.832767392],"iteration":989,"passed_time":1.261618883,"remaining_time":0.01274362508},
{"learn":[1.831306706],"iteration":990,"passed_time":1.262778682,"remaining_time":0.01146822214},
{"learn":[1.830917235],"iteration":991,"passed_time":1.263914746,"remaining_time":0.01019286086},
{"learn":[1.829663906],"iteration":992,"passed_time":1.265103396,"remaining_time":0.008918150825},
{"learn":[1.828782573],"iteration":993,"passed_time":1.266153744,"remaining_time":0.007642779139},
{"learn":[1.828305553],"iteration":994,"passed_time":1.267391327,"remaining_time":0.006368800639},
{"learn":[1.826378887],"iteration":995,"passed_time":1.2685388,"remaining_time":0.005094533333},
{"learn":[1.82630029],"iteration":996,"passed_time":1.26973168,"remaining_time":0.003820657011},
{"learn":[1.825883687],"iteration":997,"passed_time":1.270817846,"remaining_time":0.002546729149},
{"learn":[1.825795286],"iteration":998,"passed_time":1.27190106,"remaining_time":0.001273174234},
{"learn":[1.82524822],"iteration":999,"passed_time":1.272953546,"remaining_time":0}
]}